{
  "date": "Fri Jan 25 00:03:45 GMT+01:00 2019",
  "item": "libro",
  "item_index": 30,
  "movement_points": [
    {
      "time": 0,
      "component": 0,
      "x": 730.0,
      "y": 334.0
    },
    {
      "time": 11,
      "component": 0,
      "x": 730.0,
      "y": 334.0
    },
    {
      "time": 27,
      "component": 0,
      "x": 730.0,
      "y": 334.0
    },
    {
      "time": 44,
      "component": 0,
      "x": 730.0,
      "y": 334.0
    },
    {
      "time": 60,
      "component": 0,
      "x": 730.0,
      "y": 334.0
    },
    {
      "time": 77,
      "component": 0,
      "x": 730.0,
      "y": 334.0
    },
    {
      "time": 94,
      "component": 0,
      "x": 730.0,
      "y": 334.0
    },
    {
      "time": 110,
      "component": 0,
      "x": 743.3551,
      "y": 343.9034
    },
    {
      "time": 127,
      "component": 0,
      "x": 753.1048,
      "y": 351.88385
    },
    {
      "time": 143,
      "component": 0,
      "x": 764.1525,
      "y": 359.76834
    },
    {
      "time": 160,
      "component": 0,
      "x": 776.30756,
      "y": 371.30753
    },
    {
      "time": 177,
      "component": 0,
      "x": 790.44745,
      "y": 382.2407
    },
    {
      "time": 193,
      "component": 0,
      "x": 807.9469,
      "y": 394.2979
    },
    {
      "time": 210,
      "component": 0,
      "x": 825.99347,
      "y": 406.19608
    },
    {
      "time": 226,
      "component": 0,
      "x": 842.79,
      "y": 419.1933
    },
    {
      "time": 243,
      "component": 0,
      "x": 859.5684,
      "y": 430.1763
    },
    {
      "time": 260,
      "component": 0,
      "x": 873.5125,
      "y": 440.08035
    },
    {
      "time": 276,
      "component": 0,
      "x": 887.3668,
      "y": 450.97632
    },
    {
      "time": 293,
      "component": 0,
      "x": 903.43506,
      "y": 462.89694
    },
    {
      "time": 310,
      "component": 0,
      "x": 918.4936,
      "y": 474.28024
    },
    {
      "time": 326,
      "component": 0,
      "x": 932.3577,
      "y": 481.58188
    },
    {
      "time": 343,
      "component": 0,
      "x": 945.2836,
      "y": 492.0697
    },
    {
      "time": 360,
      "component": 0,
      "x": 957.28516,
      "y": 500.07095
    },
    {
      "time": 377,
      "component": 0,
      "x": 970.2801,
      "y": 506.64005
    },
    {
      "time": 393,
      "component": 0,
      "x": 978.8146,
      "y": 510.4073
    },
    {
      "time": 410,
      "component": 0,
      "x": 985.6128,
      "y": 515.6128
    },
    {
      "time": 426,
      "component": 0,
      "x": 991.60474,
      "y": 519.40314
    },
    {
      "time": 443,
      "component": 0,
      "x": 997.64215,
      "y": 522.21405
    },
    {
      "time": 460,
      "component": 0,
      "x": 1000.4271,
      "y": 524.0
    },
    {
      "time": 476,
      "component": 0,
      "x": 1003.42596,
      "y": 526.213
    },
    {
      "time": 493,
      "component": 0,
      "x": 1007.42596,
      "y": 530.42596
    },
    {
      "time": 510,
      "component": 0,
      "x": 1011.4031,
      "y": 534.4031
    },
    {
      "time": 526,
      "component": 0,
      "x": 1016.4035,
      "y": 539.4035
    },
    {
      "time": 543,
      "component": 0,
      "x": 1023.6408,
      "y": 543.6408
    },
    {
      "time": 559,
      "component": 0,
      "x": 1031.8177,
      "y": 548.6133
    },
    {
      "time": 576,
      "component": 0,
      "x": 1039.9126,
      "y": 553.4563
    },
    {
      "time": 593,
      "component": 0,
      "x": 1045.6052,
      "y": 556.2018
    },
    {
      "time": 611,
      "component": 0,
      "x": 1050.4083,
      "y": 559.20416
    },
    {
      "time": 626,
      "component": 0,
      "x": 1052.2095,
      "y": 561.2094
    },
    {
      "time": 636,
      "component": 0,
      "x": 1052.0,
      "y": 561.0
    },
    {
      "time": 1437,
      "component": 1,
      "x": 1056.0,
      "y": 546.0
    },
    {
      "time": 1443,
      "component": 1,
      "x": 1056.0,
      "y": 546.0
    },
    {
      "time": 1459,
      "component": 1,
      "x": 1056.0,
      "y": 546.0
    },
    {
      "time": 1475,
      "component": 1,
      "x": 1056.0,
      "y": 546.0
    },
    {
      "time": 1492,
      "component": 1,
      "x": 1068.861,
      "y": 536.3543
    },
    {
      "time": 1508,
      "component": 1,
      "x": 1076.875,
      "y": 529.12494
    },
    {
      "time": 1525,
      "component": 1,
      "x": 1083.6713,
      "y": 524.5525
    },
    {
      "time": 1541,
      "component": 1,
      "x": 1089.6533,
      "y": 520.56445
    },
    {
      "time": 1558,
      "component": 1,
      "x": 1092.2218,
      "y": 518.77814
    },
    {
      "time": 1575,
      "component": 1,
      "x": 1095.2156,
      "y": 517.0
    },
    {
      "time": 1592,
      "component": 1,
      "x": 1096.195,
      "y": 516.0
    },
    {
      "time": 1608,
      "component": 1,
      "x": 1096.0,
      "y": 516.0
    },
    {
      "time": 1625,
      "component": 1,
      "x": 1096.0,
      "y": 516.0
    },
    {
      "time": 1641,
      "component": 1,
      "x": 1096.0,
      "y": 516.0
    },
    {
      "time": 1658,
      "component": 1,
      "x": 1096.0,
      "y": 516.0
    },
    {
      "time": 1675,
      "component": 1,
      "x": 1096.0,
      "y": 517.0
    },
    {
      "time": 2203,
      "component": 2,
      "x": 729.0,
      "y": 360.0
    },
    {
      "time": 2208,
      "component": 2,
      "x": 729.0,
      "y": 360.0
    },
    {
      "time": 2224,
      "component": 2,
      "x": 729.0,
      "y": 360.0
    },
    {
      "time": 2241,
      "component": 2,
      "x": 727.7697,
      "y": 367.38156
    },
    {
      "time": 2257,
      "component": 2,
      "x": 728.0,
      "y": 382.74612
    },
    {
      "time": 2274,
      "component": 2,
      "x": 731.43115,
      "y": 406.5868
    },
    {
      "time": 2290,
      "component": 2,
      "x": 741.01984,
      "y": 437.05954
    },
    {
      "time": 2307,
      "component": 2,
      "x": 751.1237,
      "y": 467.5959
    },
    {
      "time": 2324,
      "component": 2,
      "x": 763.31726,
      "y": 501.7323
    },
    {
      "time": 2340,
      "component": 2,
      "x": 772.9992,
      "y": 532.9976
    },
    {
      "time": 2357,
      "component": 2,
      "x": 785.34467,
      "y": 562.1376
    },
    {
      "time": 2374,
      "component": 2,
      "x": 794.8817,
      "y": 587.11615
    },
    {
      "time": 2390,
      "component": 2,
      "x": 800.6826,
      "y": 608.2753
    },
    {
      "time": 2407,
      "component": 2,
      "x": 808.853,
      "y": 630.559
    },
    {
      "time": 2425,
      "component": 2,
      "x": 815.6654,
      "y": 651.8299
    },
    {
      "time": 2441,
      "component": 2,
      "x": 821.6762,
      "y": 675.7049
    },
    {
      "time": 2457,
      "component": 2,
      "x": 827.6396,
      "y": 697.3452
    },
    {
      "time": 2474,
      "component": 2,
      "x": 831.44666,
      "y": 722.9033
    },
    {
      "time": 2491,
      "component": 2,
      "x": 834.2154,
      "y": 744.369
    },
    {
      "time": 2507,
      "component": 2,
      "x": 836.1958,
      "y": 763.9579
    },
    {
      "time": 2524,
      "component": 2,
      "x": 837.204,
      "y": 781.83594
    },
    {
      "time": 2540,
      "component": 2,
      "x": 838.1881,
      "y": 796.31665
    },
    {
      "time": 2557,
      "component": 2,
      "x": 838.0,
      "y": 803.86273
    },
    {
      "time": 2574,
      "component": 2,
      "x": 840.2022,
      "y": 810.60657
    },
    {
      "time": 2590,
      "component": 2,
      "x": 841.16437,
      "y": 818.49316
    },
    {
      "time": 2607,
      "component": 2,
      "x": 841.0,
      "y": 825.48083
    },
    {
      "time": 2624,
      "component": 2,
      "x": 842.0,
      "y": 831.593
    },
    {
      "time": 2640,
      "component": 2,
      "x": 842.0,
      "y": 836.6312
    },
    {
      "time": 2657,
      "component": 2,
      "x": 842.0,
      "y": 840.4323
    },
    {
      "time": 2674,
      "component": 2,
      "x": 842.0,
      "y": 842.16486
    },
    {
      "time": 2690,
      "component": 2,
      "x": 842.0,
      "y": 845.17993
    },
    {
      "time": 2707,
      "component": 2,
      "x": 842.0,
      "y": 845.0
    },
    {
      "time": 2724,
      "component": 2,
      "x": 842.0,
      "y": 846.2212
    },
    {
      "time": 2740,
      "component": 2,
      "x": 842.0,
      "y": 846.0
    },
    {
      "time": 2757,
      "component": 2,
      "x": 842.0,
      "y": 846.0
    },
    {
      "time": 2774,
      "component": 2,
      "x": 842.0,
      "y": 846.0
    },
    {
      "time": 2790,
      "component": 2,
      "x": 842.0,
      "y": 846.0
    },
    {
      "time": 2807,
      "component": 2,
      "x": 842.0,
      "y": 846.0
    },
    {
      "time": 2824,
      "component": 2,
      "x": 842.0,
      "y": 846.0
    },
    {
      "time": 2840,
      "component": 2,
      "x": 842.0,
      "y": 846.0
    },
    {
      "time": 2857,
      "component": 2,
      "x": 842.0,
      "y": 846.0
    },
    {
      "time": 2873,
      "component": 2,
      "x": 842.0,
      "y": 846.0
    },
    {
      "time": 2890,
      "component": 2,
      "x": 842.0,
      "y": 846.0
    },
    {
      "time": 2907,
      "component": 2,
      "x": 842.0,
      "y": 846.0
    },
    {
      "time": 2923,
      "component": 2,
      "x": 842.0,
      "y": 846.0
    },
    {
      "time": 2940,
      "component": 2,
      "x": 842.0,
      "y": 846.0
    },
    {
      "time": 2956,
      "component": 2,
      "x": 843.0,
      "y": 846.0
    },
    {
      "time": 2973,
      "component": 2,
      "x": 848.6533,
      "y": 846.0
    },
    {
      "time": 2990,
      "component": 2,
      "x": 860.3011,
      "y": 843.78314
    },
    {
      "time": 3007,
      "component": 2,
      "x": 875.4819,
      "y": 843.0
    },
    {
      "time": 3023,
      "component": 2,
      "x": 891.7283,
      "y": 842.0
    },
    {
      "time": 3039,
      "component": 2,
      "x": 911.1548,
      "y": 843.21545
    },
    {
      "time": 3056,
      "component": 2,
      "x": 932.1135,
      "y": 846.21136
    },
    {
      "time": 3073,
      "component": 2,
      "x": 951.14154,
      "y": 850.4283
    },
    {
      "time": 3090,
      "component": 2,
      "x": 973.3506,
      "y": 855.64105
    },
    {
      "time": 3107,
      "component": 2,
      "x": 995.36584,
      "y": 860.64526
    },
    {
      "time": 3123,
      "component": 2,
      "x": 1017.1387,
      "y": 867.85547
    },
    {
      "time": 3140,
      "component": 2,
      "x": 1039.4044,
      "y": 872.43713
    },
    {
      "time": 3156,
      "component": 2,
      "x": 1058.9368,
      "y": 878.64557
    },
    {
      "time": 3173,
      "component": 2,
      "x": 1076.7229,
      "y": 884.6461
    },
    {
      "time": 3189,
      "component": 2,
      "x": 1091.5302,
      "y": 891.8744
    },
    {
      "time": 3206,
      "component": 2,
      "x": 1102.0967,
      "y": 897.658
    },
    {
      "time": 3223,
      "component": 2,
      "x": 1110.8602,
      "y": 901.215
    },
    {
      "time": 3239,
      "component": 2,
      "x": 1116.6498,
      "y": 906.6497
    },
    {
      "time": 3256,
      "component": 2,
      "x": 1118.0,
      "y": 908.2193
    },
    {
      "time": 3273,
      "component": 2,
      "x": 1120.2208,
      "y": 909.22076
    },
    {
      "time": 3289,
      "component": 2,
      "x": 1123.44,
      "y": 910.22
    },
    {
      "time": 3817,
      "component": 3,
      "x": 1121.0,
      "y": 537.0
    },
    {
      "time": 3822,
      "component": 3,
      "x": 1121.0,
      "y": 537.0
    },
    {
      "time": 3839,
      "component": 3,
      "x": 1121.0,
      "y": 537.0
    },
    {
      "time": 3855,
      "component": 3,
      "x": 1121.0,
      "y": 537.0
    },
    {
      "time": 3872,
      "component": 3,
      "x": 1121.0,
      "y": 537.0
    },
    {
      "time": 3888,
      "component": 3,
      "x": 1121.0,
      "y": 537.0
    },
    {
      "time": 3905,
      "component": 3,
      "x": 1121.0,
      "y": 537.0
    },
    {
      "time": 3922,
      "component": 3,
      "x": 1124.3999,
      "y": 522.60034
    },
    {
      "time": 3939,
      "component": 3,
      "x": 1132.8632,
      "y": 506.48956
    },
    {
      "time": 3955,
      "component": 3,
      "x": 1143.0654,
      "y": 490.50833
    },
    {
      "time": 3972,
      "component": 3,
      "x": 1158.7516,
      "y": 472.2484
    },
    {
      "time": 3988,
      "component": 3,
      "x": 1174.746,
      "y": 456.4723
    },
    {
      "time": 4005,
      "component": 3,
      "x": 1192.8656,
      "y": 441.549
    },
    {
      "time": 4022,
      "component": 3,
      "x": 1210.9086,
      "y": 427.7276
    },
    {
      "time": 4039,
      "component": 3,
      "x": 1226.6785,
      "y": 414.74115
    },
    {
      "time": 4055,
      "component": 3,
      "x": 1238.2069,
      "y": 402.99423
    },
    {
      "time": 4072,
      "component": 3,
      "x": 1246.8566,
      "y": 392.92935
    },
    {
      "time": 4089,
      "component": 3,
      "x": 1252.4097,
      "y": 384.18073
    },
    {
      "time": 4105,
      "component": 3,
      "x": 1257.418,
      "y": 379.58206
    },
    {
      "time": 4122,
      "component": 3,
      "x": 1257.0,
      "y": 379.0
    },
    {
      "time": 4139,
      "component": 3,
      "x": 1258.0,
      "y": 378.0
    },
    {
      "time": 4155,
      "component": 3,
      "x": 1258.0,
      "y": 378.0
    },
    {
      "time": 4172,
      "component": 3,
      "x": 1258.0,
      "y": 378.0
    },
    {
      "time": 4188,
      "component": 3,
      "x": 1259.0,
      "y": 378.0
    },
    {
      "time": 4205,
      "component": 3,
      "x": 1261.2075,
      "y": 379.20752
    },
    {
      "time": 4222,
      "component": 3,
      "x": 1265.4218,
      "y": 385.63263
    },
    {
      "time": 4238,
      "component": 3,
      "x": 1270.6367,
      "y": 392.63666
    },
    {
      "time": 4255,
      "component": 3,
      "x": 1275.6008,
      "y": 400.8011
    },
    {
      "time": 4272,
      "component": 3,
      "x": 1280.6278,
      "y": 407.6278
    },
    {
      "time": 4288,
      "component": 3,
      "x": 1285.6321,
      "y": 415.84277
    },
    {
      "time": 4305,
      "component": 3,
      "x": 1290.6277,
      "y": 421.41843
    },
    {
      "time": 4322,
      "component": 3,
      "x": 1294.4095,
      "y": 427.61426
    },
    {
      "time": 4338,
      "component": 3,
      "x": 1297.2102,
      "y": 433.63077
    },
    {
      "time": 4355,
      "component": 3,
      "x": 1300.2084,
      "y": 437.62512
    },
    {
      "time": 4372,
      "component": 3,
      "x": 1303.4274,
      "y": 443.6411
    },
    {
      "time": 4388,
      "component": 3,
      "x": 1306.4193,
      "y": 449.41925
    },
    {
      "time": 4405,
      "component": 3,
      "x": 1308.2122,
      "y": 457.84845
    },
    {
      "time": 4422,
      "component": 3,
      "x": 1311.2131,
      "y": 464.63937
    },
    {
      "time": 4438,
      "component": 3,
      "x": 1313.2123,
      "y": 472.84924
    },
    {
      "time": 4455,
      "component": 3,
      "x": 1316.21,
      "y": 479.83963
    },
    {
      "time": 4472,
      "component": 3,
      "x": 1319.4274,
      "y": 486.8548
    },
    {
      "time": 4488,
      "component": 3,
      "x": 1323.4299,
      "y": 494.85992
    },
    {
      "time": 4505,
      "component": 3,
      "x": 1327.4198,
      "y": 502.83963
    },
    {
      "time": 4522,
      "component": 3,
      "x": 1332.435,
      "y": 509.65262
    },
    {
      "time": 4538,
      "component": 3,
      "x": 1339.7881,
      "y": 517.78815
    },
    {
      "time": 4555,
      "component": 3,
      "x": 1344.4242,
      "y": 524.6363
    },
    {
      "time": 4571,
      "component": 3,
      "x": 1349.4321,
      "y": 528.4322
    },
    {
      "time": 4588,
      "component": 3,
      "x": 1353.4175,
      "y": 533.4175
    },
    {
      "time": 4604,
      "component": 3,
      "x": 1355.2015,
      "y": 536.4032
    },
    {
      "time": 4621,
      "component": 3,
      "x": 1358.4224,
      "y": 540.42236
    },
    {
      "time": 4638,
      "component": 3,
      "x": 1361.4082,
      "y": 546.81647
    },
    {
      "time": 4654,
      "component": 3,
      "x": 1365.4248,
      "y": 555.8496
    },
    {
      "time": 4671,
      "component": 3,
      "x": 1369.4197,
      "y": 565.04926
    },
    {
      "time": 4688,
      "component": 3,
      "x": 1373.4252,
      "y": 575.0629
    },
    {
      "time": 4704,
      "component": 3,
      "x": 1377.4296,
      "y": 587.2885
    },
    {
      "time": 4721,
      "component": 3,
      "x": 1379.2114,
      "y": 601.6918
    },
    {
      "time": 4737,
      "component": 3,
      "x": 1381.2144,
      "y": 613.28595
    },
    {
      "time": 4754,
      "component": 3,
      "x": 1383.213,
      "y": 625.2778
    },
    {
      "time": 4771,
      "component": 3,
      "x": 1385.2151,
      "y": 636.0752
    },
    {
      "time": 4789,
      "component": 3,
      "x": 1386.2119,
      "y": 645.0593
    },
    {
      "time": 4804,
      "component": 3,
      "x": 1387.0,
      "y": 652.8573
    },
    {
      "time": 4821,
      "component": 3,
      "x": 1389.2166,
      "y": 660.64966
    },
    {
      "time": 4837,
      "component": 3,
      "x": 1390.0,
      "y": 668.8559
    },
    {
      "time": 4854,
      "component": 3,
      "x": 1392.2157,
      "y": 675.64703
    },
    {
      "time": 4871,
      "component": 3,
      "x": 1394.2137,
      "y": 682.855
    },
    {
      "time": 4888,
      "component": 3,
      "x": 1395.2128,
      "y": 690.8513
    },
    {
      "time": 4904,
      "component": 3,
      "x": 1396.2162,
      "y": 696.8646
    },
    {
      "time": 4921,
      "component": 3,
      "x": 1396.0,
      "y": 701.431
    },
    {
      "time": 4937,
      "component": 3,
      "x": 1397.0,
      "y": 705.4283
    },
    {
      "time": 4954,
      "component": 3,
      "x": 1397.0,
      "y": 705.0
    },
    {
      "time": 4971,
      "component": 3,
      "x": 1397.0,
      "y": 706.0
    },
    {
      "time": 4987,
      "component": 3,
      "x": 1397.0,
      "y": 706.0
    },
    {
      "time": 5004,
      "component": 3,
      "x": 1397.0,
      "y": 706.0
    },
    {
      "time": 5021,
      "component": 3,
      "x": 1397.0,
      "y": 706.0
    },
    {
      "time": 5037,
      "component": 3,
      "x": 1397.0,
      "y": 706.0
    },
    {
      "time": 5054,
      "component": 3,
      "x": 1397.0,
      "y": 706.0
    },
    {
      "time": 5071,
      "component": 3,
      "x": 1397.0,
      "y": 706.0
    },
    {
      "time": 5087,
      "component": 3,
      "x": 1395.7823,
      "y": 706.0
    },
    {
      "time": 5104,
      "component": 3,
      "x": 1396.0,
      "y": 706.0
    },
    {
      "time": 5121,
      "component": 3,
      "x": 1393.7825,
      "y": 707.2175
    },
    {
      "time": 5137,
      "component": 3,
      "x": 1391.791,
      "y": 708.209
    },
    {
      "time": 5154,
      "component": 3,
      "x": 1388.5906,
      "y": 710.2047
    },
    {
      "time": 5170,
      "component": 3,
      "x": 1386.7898,
      "y": 711.2102
    },
    {
      "time": 5187,
      "component": 3,
      "x": 1384.7881,
      "y": 713.2119
    },
    {
      "time": 5203,
      "component": 3,
      "x": 1382.7872,
      "y": 714.21277
    },
    {
      "time": 5220,
      "component": 3,
      "x": 1382.0,
      "y": 715.0
    },
    {
      "time": 5237,
      "component": 3,
      "x": 1381.0,
      "y": 716.2151
    },
    {
      "time": 5253,
      "component": 3,
      "x": 1379.7855,
      "y": 716.0
    },
    {
      "time": 5270,
      "component": 3,
      "x": 1378.782,
      "y": 717.0
    },
    {
      "time": 5287,
      "component": 3,
      "x": 1377.7852,
      "y": 718.0
    },
    {
      "time": 5303,
      "component": 3,
      "x": 1378.0,
      "y": 719.0
    },
    {
      "time": 5320,
      "component": 3,
      "x": 1377.0,
      "y": 719.0
    },
    {
      "time": 5337,
      "component": 3,
      "x": 1377.0,
      "y": 720.0
    },
    {
      "time": 5354,
      "component": 3,
      "x": 1376.0,
      "y": 720.0
    },
    {
      "time": 5370,
      "component": 3,
      "x": 1376.0,
      "y": 720.0
    },
    {
      "time": 5387,
      "component": 3,
      "x": 1375.0,
      "y": 720.0
    },
    {
      "time": 5403,
      "component": 3,
      "x": 1375.0,
      "y": 721.0
    },
    {
      "time": 5420,
      "component": 3,
      "x": 1373.799,
      "y": 722.201
    },
    {
      "time": 5437,
      "component": 3,
      "x": 1372.7872,
      "y": 723.21277
    },
    {
      "time": 5453,
      "component": 3,
      "x": 1369.7872,
      "y": 726.2128
    },
    {
      "time": 5470,
      "component": 3,
      "x": 1366.5955,
      "y": 729.4046
    },
    {
      "time": 5487,
      "component": 3,
      "x": 1361.3647,
      "y": 732.2118
    },
    {
      "time": 5504,
      "component": 3,
      "x": 1356.389,
      "y": 736.4073
    },
    {
      "time": 5520,
      "component": 3,
      "x": 1350.3582,
      "y": 741.64185
    },
    {
      "time": 5536,
      "component": 3,
      "x": 1342.1461,
      "y": 748.8539
    },
    {
      "time": 5553,
      "component": 3,
      "x": 1335.3535,
      "y": 753.6464
    },
    {
      "time": 5570,
      "component": 3,
      "x": 1329.3685,
      "y": 759.42096
    },
    {
      "time": 5587,
      "component": 3,
      "x": 1323.3567,
      "y": 764.4289
    },
    {
      "time": 5603,
      "component": 3,
      "x": 1320.5713,
      "y": 767.4288
    },
    {
      "time": 5620,
      "component": 3,
      "x": 1315.3551,
      "y": 772.64496
    },
    {
      "time": 5637,
      "component": 3,
      "x": 1307.1361,
      "y": 780.8639
    },
    {
      "time": 5653,
      "component": 3,
      "x": 1296.9218,
      "y": 790.0782
    },
    {
      "time": 5670,
      "component": 3,
      "x": 1285.9197,
      "y": 801.08026
    },
    {
      "time": 5687,
      "component": 3,
      "x": 1273.6831,
      "y": 813.0974
    },
    {
      "time": 5703,
      "component": 3,
      "x": 1259.4753,
      "y": 826.3069
    },
    {
      "time": 5720,
      "component": 3,
      "x": 1240.8458,
      "y": 842.9388
    },
    {
      "time": 5737,
      "component": 3,
      "x": 1223.0555,
      "y": 859.9444
    },
    {
      "time": 5753,
      "component": 3,
      "x": 1207.2637,
      "y": 875.7363
    },
    {
      "time": 5770,
      "component": 3,
      "x": 1192.5936,
      "y": 889.40643
    },
    {
      "time": 5787,
      "component": 3,
      "x": 1179.694,
      "y": 902.306
    },
    {
      "time": 5803,
      "component": 3,
      "x": 1168.9141,
      "y": 914.30304
    },
    {
      "time": 5820,
      "component": 3,
      "x": 1161.1206,
      "y": 923.0992
    },
    {
      "time": 5837,
      "component": 3,
      "x": 1155.354,
      "y": 930.8613
    },
    {
      "time": 5853,
      "component": 3,
      "x": 1154.7822,
      "y": 931.21783
    },
    {
      "time": 5870,
      "component": 3,
      "x": 1152.8064,
      "y": 935.38715
    },
    {
      "time": 5886,
      "component": 3,
      "x": 1152.0,
      "y": 939.42975
    },
    {
      "time": 5903,
      "component": 3,
      "x": 1152.0,
      "y": 941.2232
    },
    {
      "time": 6865,
      "component": 4,
      "x": 1068.0,
      "y": 572.0
    },
    {
      "time": 6885,
      "component": 4,
      "x": 1068.0,
      "y": 572.0
    },
    {
      "time": 6902,
      "component": 4,
      "x": 1068.0,
      "y": 572.0
    },
    {
      "time": 6918,
      "component": 4,
      "x": 1068.0,
      "y": 572.0
    },
    {
      "time": 6935,
      "component": 4,
      "x": 1068.0,
      "y": 572.0
    },
    {
      "time": 6951,
      "component": 4,
      "x": 1068.0,
      "y": 584.1792
    },
    {
      "time": 6968,
      "component": 4,
      "x": 1071.4158,
      "y": 617.74194
    },
    {
      "time": 6985,
      "component": 4,
      "x": 1076.4286,
      "y": 657.2856
    },
    {
      "time": 7001,
      "component": 4,
      "x": 1083.8445,
      "y": 693.8004
    },
    {
      "time": 7018,
      "component": 4,
      "x": 1090.8383,
      "y": 727.56287
    },
    {
      "time": 7035,
      "component": 4,
      "x": 1098.8566,
      "y": 766.283
    },
    {
      "time": 7051,
      "component": 4,
      "x": 1105.6332,
      "y": 804.00977
    },
    {
      "time": 7068,
      "component": 4,
      "x": 1111.6213,
      "y": 840.52106
    },
    {
      "time": 7085,
      "component": 4,
      "x": 1116.3978,
      "y": 870.9836
    },
    {
      "time": 7102,
      "component": 4,
      "x": 1119.2126,
      "y": 892.33966
    },
    {
      "time": 7118,
      "component": 4,
      "x": 1123.4138,
      "y": 914.27625
    },
    {
      "time": 7135,
      "component": 4,
      "x": 1127.4205,
      "y": 931.6824
    },
    {
      "time": 7153,
      "component": 4,
      "x": 1129.2131,
      "y": 947.4915
    },
    {
      "time": 7168,
      "component": 4,
      "x": 1132.2139,
      "y": 959.2834
    },
    {
      "time": 7178,
      "component": 4,
      "x": 1132.0,
      "y": 962.0
    },
    {
      "time": 7564,
      "component": 5,
      "x": 1136.0,
      "y": 554.0
    },
    {
      "time": 7584,
      "component": 5,
      "x": 1136.0,
      "y": 554.0
    },
    {
      "time": 7601,
      "component": 5,
      "x": 1136.0,
      "y": 554.0
    },
    {
      "time": 7618,
      "component": 5,
      "x": 1136.0,
      "y": 554.0
    },
    {
      "time": 7634,
      "component": 5,
      "x": 1135.0,
      "y": 564.97394
    },
    {
      "time": 7651,
      "component": 5,
      "x": 1136.2163,
      "y": 581.94714
    },
    {
      "time": 7667,
      "component": 5,
      "x": 1136.0,
      "y": 602.3797
    },
    {
      "time": 7684,
      "component": 5,
      "x": 1136.0,
      "y": 626.5182
    },
    {
      "time": 7701,
      "component": 5,
      "x": 1136.0,
      "y": 652.74506
    },
    {
      "time": 7717,
      "component": 5,
      "x": 1138.2122,
      "y": 678.75745
    },
    {
      "time": 7734,
      "component": 5,
      "x": 1140.2098,
      "y": 705.72815
    },
    {
      "time": 7751,
      "component": 5,
      "x": 1143.4076,
      "y": 730.4456
    },
    {
      "time": 7767,
      "component": 5,
      "x": 1147.4167,
      "y": 754.50055
    },
    {
      "time": 7784,
      "component": 5,
      "x": 1149.2063,
      "y": 781.8873
    },
    {
      "time": 7801,
      "component": 5,
      "x": 1153.4263,
      "y": 807.77106
    },
    {
      "time": 7817,
      "component": 5,
      "x": 1156.4176,
      "y": 832.5056
    },
    {
      "time": 7834,
      "component": 5,
      "x": 1160.4208,
      "y": 853.3145
    },
    {
      "time": 7851,
      "component": 5,
      "x": 1162.209,
      "y": 868.672
    },
    {
      "time": 7867,
      "component": 5,
      "x": 1164.0,
      "y": 881.1702
    },
    {
      "time": 7884,
      "component": 5,
      "x": 1166.2023,
      "y": 891.0116
    },
    {
      "time": 7901,
      "component": 5,
      "x": 1167.0,
      "y": 896.4157
    },
    {
      "time": 7917,
      "component": 5,
      "x": 1167.0,
      "y": 896.0
    },
    {
      "time": 9611,
      "component": 6,
      "x": 1223.0,
      "y": 608.0
    },
    {
      "time": 9632,
      "component": 6,
      "x": 1223.0,
      "y": 608.0
    },
    {
      "time": 9649,
      "component": 6,
      "x": 1223.0,
      "y": 608.0
    },
    {
      "time": 9665,
      "component": 6,
      "x": 1223.0,
      "y": 608.0
    },
    {
      "time": 9682,
      "component": 6,
      "x": 1223.0,
      "y": 608.0
    },
    {
      "time": 9698,
      "component": 6,
      "x": 1223.0,
      "y": 608.0
    },
    {
      "time": 9715,
      "component": 6,
      "x": 1223.0,
      "y": 608.0
    },
    {
      "time": 9732,
      "component": 6,
      "x": 1223.0,
      "y": 608.0
    },
    {
      "time": 9748,
      "component": 6,
      "x": 1235.0162,
      "y": 598.187
    },
    {
      "time": 9765,
      "component": 6,
      "x": 1246.0333,
      "y": 587.9667
    },
    {
      "time": 9781,
      "component": 6,
      "x": 1258.262,
      "y": 580.1586
    },
    {
      "time": 9798,
      "component": 6,
      "x": 1269.056,
      "y": 569.944
    },
    {
      "time": 9815,
      "component": 6,
      "x": 1279.9161,
      "y": 561.0838
    },
    {
      "time": 9832,
      "component": 6,
      "x": 1288.8102,
      "y": 553.39233
    },
    {
      "time": 9842,
      "component": 6,
      "x": 1291.0,
      "y": 550.0
    },
    {
      "time": 10196,
      "component": 7,
      "x": 1273.0,
      "y": 656.0
    },
    {
      "time": 10201,
      "component": 7,
      "x": 1273.0,
      "y": 656.0
    },
    {
      "time": 10210,
      "component": 7,
      "x": 1273.0,
      "y": 656.0
    },
    {
      "time": 10228,
      "component": 7,
      "x": 1273.0,
      "y": 656.0
    },
    {
      "time": 10237,
      "component": 7,
      "x": 1273.0,
      "y": 656.0
    },
    {
      "time": 10257,
      "component": 7,
      "x": 1273.0,
      "y": 656.0
    },
    {
      "time": 10267,
      "component": 7,
      "x": 1273.0,
      "y": 656.0
    },
    {
      "time": 10282,
      "component": 7,
      "x": 1278.9965,
      "y": 648.8043
    },
    {
      "time": 10299,
      "component": 7,
      "x": 1289.9706,
      "y": 640.2235
    },
    {
      "time": 10315,
      "component": 7,
      "x": 1298.7678,
      "y": 634.4241
    },
    {
      "time": 10330,
      "component": 7,
      "x": 1306.5682,
      "y": 631.8106
    },
    {
      "time": 10342,
      "component": 7,
      "x": 1309.0,
      "y": 630.0
    },
    {
      "time": 10625,
      "component": 8,
      "x": 1274.0,
      "y": 739.0
    },
    {
      "time": 10631,
      "component": 8,
      "x": 1274.0,
      "y": 739.0
    },
    {
      "time": 10648,
      "component": 8,
      "x": 1274.0,
      "y": 739.0
    },
    {
      "time": 10665,
      "component": 8,
      "x": 1274.0,
      "y": 739.0
    },
    {
      "time": 10680,
      "component": 8,
      "x": 1274.0,
      "y": 739.0
    },
    {
      "time": 10697,
      "component": 8,
      "x": 1274.0,
      "y": 739.0
    },
    {
      "time": 10714,
      "component": 8,
      "x": 1274.0,
      "y": 739.0
    },
    {
      "time": 10730,
      "component": 8,
      "x": 1274.0,
      "y": 739.0
    },
    {
      "time": 10747,
      "component": 8,
      "x": 1274.0,
      "y": 739.0
    },
    {
      "time": 10763,
      "component": 8,
      "x": 1288.4735,
      "y": 719.7019
    },
    {
      "time": 10774,
      "component": 8,
      "x": 1296.0,
      "y": 707.0
    },
    {
      "time": 11868,
      "component": 9,
      "x": 1129.0,
      "y": 487.0
    },
    {
      "time": 11879,
      "component": 9,
      "x": 1129.0,
      "y": 487.0
    },
    {
      "time": 11895,
      "component": 9,
      "x": 1129.0,
      "y": 487.0
    },
    {
      "time": 11912,
      "component": 9,
      "x": 1129.0,
      "y": 487.0
    },
    {
      "time": 11929,
      "component": 9,
      "x": 1129.0,
      "y": 487.0
    },
    {
      "time": 11945,
      "component": 9,
      "x": 1139.666,
      "y": 479.8893
    },
    {
      "time": 11962,
      "component": 9,
      "x": 1146.6688,
      "y": 475.49838
    },
    {
      "time": 11978,
      "component": 9,
      "x": 1154.8123,
      "y": 465.9847
    },
    {
      "time": 11995,
      "component": 9,
      "x": 1163.8281,
      "y": 455.7578
    },
    {
      "time": 12012,
      "component": 9,
      "x": 1176.3916,
      "y": 443.8072
    },
    {
      "time": 12028,
      "component": 9,
      "x": 1191.6499,
      "y": 428.5563
    },
    {
      "time": 12045,
      "component": 9,
      "x": 1210.9196,
      "y": 413.65628
    },
    {
      "time": 12062,
      "component": 9,
      "x": 1228.8158,
      "y": 400.99124
    },
    {
      "time": 12078,
      "component": 9,
      "x": 1244.3981,
      "y": 387.8017
    },
    {
      "time": 12674,
      "component": 10,
      "x": 1104.0,
      "y": 525.0
    },
    {
      "time": 12678,
      "component": 10,
      "x": 1104.0,
      "y": 525.0
    },
    {
      "time": 12694,
      "component": 10,
      "x": 1104.0,
      "y": 525.0
    },
    {
      "time": 12711,
      "component": 10,
      "x": 1104.0,
      "y": 525.0
    },
    {
      "time": 12727,
      "component": 10,
      "x": 1111.6038,
      "y": 510.99374
    },
    {
      "time": 12744,
      "component": 10,
      "x": 1118.82,
      "y": 498.77008
    },
    {
      "time": 12760,
      "component": 10,
      "x": 1127.9861,
      "y": 482.225
    },
    {
      "time": 12778,
      "component": 10,
      "x": 1139.0363,
      "y": 466.44562
    },
    {
      "time": 12794,
      "component": 10,
      "x": 1154.649,
      "y": 449.1448
    },
    {
      "time": 12811,
      "component": 10,
      "x": 1170.6812,
      "y": 429.89862
    },
    {
      "time": 12827,
      "component": 10,
      "x": 1186.6716,
      "y": 412.11935
    },
    {
      "time": 12844,
      "component": 10,
      "x": 1204.8499,
      "y": 396.35565
    },
    {
      "time": 12860,
      "component": 10,
      "x": 1225.103,
      "y": 380.5279
    },
    {
      "time": 13340,
      "component": 11,
      "x": 1114.0,
      "y": 509.0
    },
    {
      "time": 13360,
      "component": 11,
      "x": 1114.0,
      "y": 509.0
    },
    {
      "time": 13377,
      "component": 11,
      "x": 1114.0,
      "y": 509.0
    },
    {
      "time": 13393,
      "component": 11,
      "x": 1109.8066,
      "y": 493.0333
    },
    {
      "time": 13410,
      "component": 11,
      "x": 1110.0,
      "y": 479.68933
    },
    {
      "time": 13427,
      "component": 11,
      "x": 1112.3744,
      "y": 467.6897
    },
    {
      "time": 13443,
      "component": 11,
      "x": 1117.5953,
      "y": 452.2141
    },
    {
      "time": 13460,
      "component": 11,
      "x": 1129.0856,
      "y": 435.37164
    },
    {
      "time": 13477,
      "component": 11,
      "x": 1142.3727,
      "y": 419.43124
    },
    {
      "time": 13494,
      "component": 11,
      "x": 1156.6699,
      "y": 406.5686
    },
    {
      "time": 13510,
      "component": 11,
      "x": 1171.902,
      "y": 397.81128
    },
    {
      "time": 13527,
      "component": 11,
      "x": 1187.7993,
      "y": 385.65048
    },
    {
      "time": 14031,
      "component": 12,
      "x": 1121.0,
      "y": 523.0
    },
    {
      "time": 14037,
      "component": 12,
      "x": 1121.0,
      "y": 523.0
    },
    {
      "time": 14045,
      "component": 12,
      "x": 1121.0,
      "y": 523.0
    },
    {
      "time": 14060,
      "component": 12,
      "x": 1121.0,
      "y": 523.0
    },
    {
      "time": 14076,
      "component": 12,
      "x": 1118.7582,
      "y": 513.03253
    },
    {
      "time": 14093,
      "component": 12,
      "x": 1119.0,
      "y": 505.0628
    },
    {
      "time": 14109,
      "component": 12,
      "x": 1122.4879,
      "y": 484.56055
    },
    {
      "time": 14126,
      "component": 12,
      "x": 1127.7384,
      "y": 462.0466
    },
    {
      "time": 14143,
      "component": 12,
      "x": 1132.4928,
      "y": 434.55017
    },
    {
      "time": 14159,
      "component": 12,
      "x": 1135.2483,
      "y": 406.52423
    },
    {
      "time": 14176,
      "component": 12,
      "x": 1140.7329,
      "y": 383.06824
    },
    {
      "time": 14193,
      "component": 12,
      "x": 1145.7402,
      "y": 363.7794
    },
    {
      "time": 14209,
      "component": 12,
      "x": 1155.217,
      "y": 352.78296
    },
    {
      "time": 14226,
      "component": 12,
      "x": 1169.708,
      "y": 345.26797
    }
  ],
  "sampled_points": [
    {
      "component": 0,
      "x": 730.0,
      "y": 334.0
    },
    {
      "component": 0,
      "x": 733.6005,
      "y": 336.66998
    },
    {
      "component": 0,
      "x": 738.19556,
      "y": 340.0824
    },
    {
      "component": 0,
      "x": 742.41284,
      "y": 343.2833
    },
    {
      "component": 0,
      "x": 746.20776,
      "y": 346.25894
    },
    {
      "component": 0,
      "x": 749.7954,
      "y": 349.16037
    },
    {
      "component": 0,
      "x": 753.6964,
      "y": 352.19843
    },
    {
      "component": 0,
      "x": 757.78705,
      "y": 355.22247
    },
    {
      "component": 0,
      "x": 761.5875,
      "y": 358.0378
    },
    {
      "component": 0,
      "x": 765.3957,
      "y": 361.16223
    },
    {
      "component": 0,
      "x": 769.32477,
      "y": 364.6858
    },
    {
      "component": 0,
      "x": 772.99915,
      "y": 368.10443
    },
    {
      "component": 0,
      "x": 776.72455,
      "y": 371.37595
    },
    {
      "component": 0,
      "x": 780.6159,
      "y": 374.5968
    },
    {
      "component": 0,
      "x": 784.527,
      "y": 377.6581
    },
    {
      "component": 0,
      "x": 788.32135,
      "y": 380.5135
    },
    {
      "component": 0,
      "x": 792.3354,
      "y": 383.44232
    },
    {
      "component": 0,
      "x": 796.56903,
      "y": 386.44467
    },
    {
      "component": 0,
      "x": 800.8485,
      "y": 389.40472
    },
    {
      "component": 0,
      "x": 804.95795,
      "y": 392.20975
    },
    {
      "component": 0,
      "x": 809.0971,
      "y": 395.00613
    },
    {
      "component": 0,
      "x": 813.2661,
      "y": 397.79385
    },
    {
      "component": 0,
      "x": 817.4646,
      "y": 400.5737
    },
    {
      "component": 0,
      "x": 821.6367,
      "y": 403.38913
    },
    {
      "component": 0,
      "x": 825.74066,
      "y": 406.26453
    },
    {
      "component": 0,
      "x": 829.7765,
      "y": 409.19983
    },
    {
      "component": 0,
      "x": 833.7441,
      "y": 412.1951
    },
    {
      "component": 0,
      "x": 837.79114,
      "y": 415.28418
    },
    {
      "component": 0,
      "x": 841.86066,
      "y": 418.27634
    },
    {
      "component": 0,
      "x": 845.92914,
      "y": 421.15018
    },
    {
      "component": 0,
      "x": 849.9966,
      "y": 423.9057
    },
    {
      "component": 0,
      "x": 854.33057,
      "y": 426.76178
    },
    {
      "component": 0,
      "x": 858.5986,
      "y": 429.62363
    },
    {
      "component": 0,
      "x": 862.66125,
      "y": 432.4073
    },
    {
      "component": 0,
      "x": 866.51855,
      "y": 435.1128
    },
    {
      "component": 0,
      "x": 870.52966,
      "y": 438.005
    },
    {
      "component": 0,
      "x": 874.53485,
      "y": 440.9806
    },
    {
      "component": 0,
      "x": 878.5326,
      "y": 444.03848
    },
    {
      "component": 0,
      "x": 882.384,
      "y": 447.05054
    },
    {
      "component": 0,
      "x": 886.2256,
      "y": 450.02014
    },
    {
      "component": 0,
      "x": 890.2236,
      "y": 453.0621
    },
    {
      "component": 0,
      "x": 894.3779,
      "y": 456.17645
    },
    {
      "component": 0,
      "x": 898.5197,
      "y": 459.2544
    },
    {
      "component": 0,
      "x": 902.568,
      "y": 462.27533
    },
    {
      "component": 0,
      "x": 906.54944,
      "y": 465.26074
    },
    {
      "component": 0,
      "x": 910.4642,
      "y": 468.21063
    },
    {
      "component": 0,
      "x": 914.56586,
      "y": 471.2184
    },
    {
      "component": 0,
      "x": 918.64136,
      "y": 473.96124
    },
    {
      "component": 0,
      "x": 922.9803,
      "y": 476.59027
    },
    {
      "component": 0,
      "x": 927.24915,
      "y": 478.92352
    },
    {
      "component": 0,
      "x": 931.4764,
      "y": 481.47897
    },
    {
      "component": 0,
      "x": 935.613,
      "y": 484.34253
    },
    {
      "component": 0,
      "x": 939.6891,
      "y": 487.52646
    },
    {
      "component": 0,
      "x": 943.7859,
      "y": 490.7227
    },
    {
      "component": 0,
      "x": 947.7867,
      "y": 493.66077
    },
    {
      "component": 0,
      "x": 951.7224,
      "y": 496.3609
    },
    {
      "component": 0,
      "x": 955.94226,
      "y": 499.0228
    },
    {
      "component": 0,
      "x": 960.2808,
      "y": 501.51358
    },
    {
      "component": 0,
      "x": 964.80853,
      "y": 503.87238
    },
    {
      "component": 0,
      "x": 969.2599,
      "y": 506.06708
    },
    {
      "component": 0,
      "x": 973.82465,
      "y": 508.20178
    },
    {
      "component": 0,
      "x": 978.31793,
      "y": 510.42505
    },
    {
      "component": 0,
      "x": 982.4186,
      "y": 513.1665
    },
    {
      "component": 0,
      "x": 986.5857,
      "y": 516.17883
    },
    {
      "component": 0,
      "x": 990.723,
      "y": 518.7828
    },
    {
      "component": 0,
      "x": 995.2789,
      "y": 521.1168
    },
    {
      "component": 0,
      "x": 999.49915,
      "y": 523.4089
    },
    {
      "component": 0,
      "x": 1003.32605,
      "y": 526.2586
    },
    {
      "component": 0,
      "x": 1007.0448,
      "y": 530.00714
    },
    {
      "component": 0,
      "x": 1010.4493,
      "y": 533.4493
    },
    {
      "component": 0,
      "x": 1014.06866,
      "y": 537.067
    },
    {
      "component": 0,
      "x": 1017.8535,
      "y": 540.1496
    },
    {
      "component": 0,
      "x": 1022.1451,
      "y": 542.77277
    },
    {
      "component": 0,
      "x": 1026.472,
      "y": 545.3645
    },
    {
      "component": 0,
      "x": 1030.8276,
      "y": 548.0055
    },
    {
      "component": 0,
      "x": 1035.1029,
      "y": 550.57837
    },
    {
      "component": 0,
      "x": 1039.7617,
      "y": 553.2762
    },
    {
      "component": 0,
      "x": 1043.9166,
      "y": 555.40204
    },
    {
      "component": 0,
      "x": 1048.2949,
      "y": 557.88477
    },
    {
      "component": 0,
      "x": 1052.1149,
      "y": 561.1142
    },
    {
      "component": 1,
      "x": 1056.0,
      "y": 546.0
    },
    {
      "component": 1,
      "x": 1059.5981,
      "y": 543.3014
    },
    {
      "component": 1,
      "x": 1064.0986,
      "y": 539.9152
    },
    {
      "component": 1,
      "x": 1067.962,
      "y": 536.8926
    },
    {
      "component": 1,
      "x": 1071.864,
      "y": 533.6309
    },
    {
      "component": 1,
      "x": 1075.7769,
      "y": 530.2243
    },
    {
      "component": 1,
      "x": 1079.5988,
      "y": 527.3014
    },
    {
      "component": 1,
      "x": 1083.7548,
      "y": 524.50146
    },
    {
      "component": 1,
      "x": 1088.1387,
      "y": 521.57166
    },
    {
      "component": 1,
      "x": 1091.9147,
      "y": 519.0124
    },
    {
      "component": 1,
      "x": 1096.1116,
      "y": 516.02545
    },
    {
      "component": 2,
      "x": 729.0,
      "y": 360.0
    },
    {
      "component": 2,
      "x": 728.2335,
      "y": 364.74835
    },
    {
      "component": 2,
      "x": 727.9042,
      "y": 369.75137
    },
    {
      "component": 2,
      "x": 727.8826,
      "y": 374.9091
    },
    {
      "component": 2,
      "x": 728.0723,
      "y": 379.6588
    },
    {
      "component": 2,
      "x": 728.49695,
      "y": 384.80917
    },
    {
      "component": 2,
      "x": 729.0359,
      "y": 389.6081
    },
    {
      "component": 2,
      "x": 729.73785,
      "y": 394.82062
    },
    {
      "component": 2,
      "x": 730.51996,
      "y": 399.54022
    },
    {
      "component": 2,
      "x": 731.53015,
      "y": 404.5055
    },
    {
      "component": 2,
      "x": 732.69116,
      "y": 409.41086
    },
    {
      "component": 2,
      "x": 733.94006,
      "y": 414.1227
    },
    {
      "component": 2,
      "x": 735.36096,
      "y": 419.01984
    },
    {
      "component": 2,
      "x": 736.8907,
      "y": 423.93338
    },
    {
      "component": 2,
      "x": 738.3982,
      "y": 428.68817
    },
    {
      "component": 2,
      "x": 739.9183,
      "y": 433.44446
    },
    {
      "component": 2,
      "x": 741.45087,
      "y": 438.20233
    },
    {
      "component": 2,
      "x": 742.99603,
      "y": 442.96173
    },
    {
      "component": 2,
      "x": 744.5537,
      "y": 447.7227
    },
    {
      "component": 2,
      "x": 746.1206,
      "y": 452.4753
    },
    {
      "component": 2,
      "x": 747.6214,
      "y": 456.98016
    },
    {
      "component": 2,
      "x": 749.1669,
      "y": 461.56192
    },
    {
      "component": 2,
      "x": 750.75696,
      "y": 466.22058
    },
    {
      "component": 2,
      "x": 752.3917,
      "y": 470.9562
    },
    {
      "component": 2,
      "x": 754.0711,
      "y": 475.76874
    },
    {
      "component": 2,
      "x": 755.79517,
      "y": 480.6582
    },
    {
      "component": 2,
      "x": 757.5593,
      "y": 485.61435
    },
    {
      "component": 2,
      "x": 759.2909,
      "y": 490.52252
    },
    {
      "component": 2,
      "x": 760.96967,
      "y": 495.3703
    },
    {
      "component": 2,
      "x": 762.5956,
      "y": 500.1577
    },
    {
      "component": 2,
      "x": 764.16876,
      "y": 504.88477
    },
    {
      "component": 2,
      "x": 765.6891,
      "y": 509.55145
    },
    {
      "component": 2,
      "x": 767.15656,
      "y": 514.1578
    },
    {
      "component": 2,
      "x": 768.60657,
      "y": 518.8015
    },
    {
      "component": 2,
      "x": 770.1637,
      "y": 523.6232
    },
    {
      "component": 2,
      "x": 771.7852,
      "y": 528.3936
    },
    {
      "component": 2,
      "x": 773.4712,
      "y": 533.11255
    },
    {
      "component": 2,
      "x": 775.2216,
      "y": 537.78015
    },
    {
      "component": 2,
      "x": 777.03644,
      "y": 542.39624
    },
    {
      "component": 2,
      "x": 778.9157,
      "y": 546.961
    },
    {
      "component": 2,
      "x": 780.9014,
      "y": 551.6749
    },
    {
      "component": 2,
      "x": 782.82715,
      "y": 556.31146
    },
    {
      "component": 2,
      "x": 784.677,
      "y": 560.8355
    },
    {
      "component": 2,
      "x": 786.5764,
      "y": 565.56226
    },
    {
      "component": 2,
      "x": 788.414,
      "y": 570.22473
    },
    {
      "component": 2,
      "x": 790.169,
      "y": 574.77325
    },
    {
      "component": 2,
      "x": 792.04706,
      "y": 579.8253
    },
    {
      "component": 2,
      "x": 793.767,
      "y": 584.7159
    },
    {
      "component": 2,
      "x": 795.3289,
      "y": 589.44476
    },
    {
      "component": 2,
      "x": 796.7328,
      "y": 594.01215
    },
    {
      "component": 2,
      "x": 797.99536,
      "y": 598.4683
    },
    {
      "component": 2,
      "x": 799.34235,
      "y": 603.14105
    },
    {
      "component": 2,
      "x": 800.80316,
      "y": 607.8677
    },
    {
      "component": 2,
      "x": 802.37775,
      "y": 612.6484
    },
    {
      "component": 2,
      "x": 804.0661,
      "y": 617.48303
    },
    {
      "component": 2,
      "x": 805.8259,
      "y": 622.32605
    },
    {
      "component": 2,
      "x": 807.5292,
      "y": 627.1114
    },
    {
      "component": 2,
      "x": 809.16846,
      "y": 631.849
    },
    {
      "component": 2,
      "x": 810.74365,
      "y": 636.5389
    },
    {
      "component": 2,
      "x": 812.2549,
      "y": 641.181
    },
    {
      "component": 2,
      "x": 813.6885,
      "y": 645.77234
    },
    {
      "component": 2,
      "x": 815.0855,
      "y": 650.4816
    },
    {
      "component": 2,
      "x": 816.44617,
      "y": 655.3092
    },
    {
      "component": 2,
      "x": 817.77045,
      "y": 660.25494
    },
    {
      "component": 2,
      "x": 819.05884,
      "y": 665.3045
    },
    {
      "component": 2,
      "x": 820.3343,
      "y": 670.29626
    },
    {
      "component": 2,
      "x": 821.6076,
      "y": 675.18713
    },
    {
      "component": 2,
      "x": 822.8787,
      "y": 679.9771
    },
    {
      "component": 2,
      "x": 824.14777,
      "y": 684.6662
    },
    {
      "component": 2,
      "x": 825.3806,
      "y": 689.23785
    },
    {
      "component": 2,
      "x": 826.516,
      "y": 693.9127
    },
    {
      "component": 2,
      "x": 827.55853,
      "y": 698.7562
    },
    {
      "component": 2,
      "x": 828.50824,
      "y": 703.7684
    },
    {
      "component": 2,
      "x": 829.3651,
      "y": 708.94916
    },
    {
      "component": 2,
      "x": 830.12744,
      "y": 714.0824
    },
    {
      "component": 2,
      "x": 830.8413,
      "y": 719.0246
    },
    {
      "component": 2,
      "x": 831.53094,
      "y": 723.9298
    },
    {
      "component": 2,
      "x": 832.21515,
      "y": 728.95184
    },
    {
      "component": 2,
      "x": 832.8507,
      "y": 733.7889
    },
    {
      "component": 2,
      "x": 833.4962,
      "y": 738.9246
    },
    {
      "component": 2,
      "x": 834.0956,
      "y": 743.9505
    },
    {
      "component": 2,
      "x": 834.64874,
      "y": 748.8665
    },
    {
      "component": 2,
      "x": 835.15576,
      "y": 753.67267
    },
    {
      "component": 2,
      "x": 835.6503,
      "y": 758.78754
    },
    {
      "component": 2,
      "x": 836.0811,
      "y": 763.83014
    },
    {
      "component": 2,
      "x": 836.4431,
      "y": 768.75165
    },
    {
      "component": 2,
      "x": 836.7428,
      "y": 773.6547
    },
    {
      "component": 2,
      "x": 837.0523,
      "y": 778.963
    },
    {
      "component": 2,
      "x": 837.3595,
      "y": 783.9481
    },
    {
      "component": 2,
      "x": 837.6644,
      "y": 788.6099
    },
    {
      "component": 2,
      "x": 837.96924,
      "y": 793.731
    },
    {
      "component": 2,
      "x": 838.10913,
      "y": 798.739
    },
    {
      "component": 2,
      "x": 838.27826,
      "y": 803.6128
    },
    {
      "component": 2,
      "x": 839.4493,
      "y": 808.3688
    },
    {
      "component": 2,
      "x": 840.50635,
      "y": 813.2557
    },
    {
      "component": 2,
      "x": 841.02527,
      "y": 818.4137
    },
    {
      "component": 2,
      "x": 841.0726,
      "y": 823.3633
    },
    {
      "component": 2,
      "x": 841.46216,
      "y": 828.29956
    },
    {
      "component": 2,
      "x": 841.9884,
      "y": 833.33307
    },
    {
      "component": 2,
      "x": 842.0,
      "y": 838.296
    },
    {
      "component": 2,
      "x": 842.0,
      "y": 843.1684
    },
    {
      "component": 2,
      "x": 843.9448,
      "y": 846.0
    },
    {
      "component": 2,
      "x": 848.9596,
      "y": 845.7777
    },
    {
      "component": 2,
      "x": 853.8999,
      "y": 845.0001
    },
    {
      "component": 2,
      "x": 858.5412,
      "y": 844.2343
    },
    {
      "component": 2,
      "x": 863.53296,
      "y": 843.6879
    },
    {
      "component": 2,
      "x": 868.84436,
      "y": 843.3421
    },
    {
      "component": 2,
      "x": 873.742,
      "y": 843.07806
    },
    {
      "component": 2,
      "x": 878.74725,
      "y": 842.7921
    },
    {
      "component": 2,
      "x": 883.8302,
      "y": 842.4864
    },
    {
      "component": 2,
      "x": 888.52167,
      "y": 842.3017
    },
    {
      "component": 2,
      "x": 893.4631,
      "y": 842.2911
    },
    {
      "component": 2,
      "x": 898.6543,
      "y": 842.4546
    },
    {
      "component": 2,
      "x": 903.7585,
      "y": 842.7646
    },
    {
      "component": 2,
      "x": 908.6341,
      "y": 843.1699
    },
    {
      "component": 2,
      "x": 913.60266,
      "y": 843.68335
    },
    {
      "component": 2,
      "x": 918.6641,
      "y": 844.3047
    },
    {
      "component": 2,
      "x": 923.7984,
      "y": 845.0308
    },
    {
      "component": 2,
      "x": 928.8488,
      "y": 845.8363
    },
    {
      "component": 2,
      "x": 933.7822,
      "y": 846.71576
    },
    {
      "component": 2,
      "x": 938.59875,
      "y": 847.6691
    },
    {
      "component": 2,
      "x": 943.25104,
      "y": 848.68066
    },
    {
      "component": 2,
      "x": 947.9018,
      "y": 849.7253
    },
    {
      "component": 2,
      "x": 952.73035,
      "y": 850.82556
    },
    {
      "component": 2,
      "x": 957.73663,
      "y": 851.9815
    },
    {
      "component": 2,
      "x": 962.8734,
      "y": 853.1818
    },
    {
      "component": 2,
      "x": 967.7605,
      "y": 854.324
    },
    {
      "component": 2,
      "x": 972.63824,
      "y": 855.45593
    },
    {
      "component": 2,
      "x": 977.50653,
      "y": 856.5778
    },
    {
      "component": 2,
      "x": 982.3654,
      "y": 857.6895
    },
    {
      "component": 2,
      "x": 987.2101,
      "y": 858.8104
    },
    {
      "component": 2,
      "x": 992.0401,
      "y": 860.02747
    },
    {
      "component": 2,
      "x": 996.8584,
      "y": 861.3513
    },
    {
      "component": 2,
      "x": 1001.665,
      "y": 862.78186
    },
    {
      "component": 2,
      "x": 1006.4592,
      "y": 864.3188
    },
    {
      "component": 2,
      "x": 1011.2479,
      "y": 865.8316
    },
    {
      "component": 2,
      "x": 1016.0603,
      "y": 867.21796
    },
    {
      "component": 2,
      "x": 1020.8964,
      "y": 868.47784
    },
    {
      "component": 2,
      "x": 1025.7562,
      "y": 869.61127
    },
    {
      "component": 2,
      "x": 1030.7526,
      "y": 870.6706
    },
    {
      "component": 2,
      "x": 1035.766,
      "y": 871.8179
    },
    {
      "component": 2,
      "x": 1040.6328,
      "y": 873.0524
    },
    {
      "component": 2,
      "x": 1045.353,
      "y": 874.3743
    },
    {
      "component": 2,
      "x": 1050.0022,
      "y": 875.806
    },
    {
      "component": 2,
      "x": 1054.9011,
      "y": 877.3782
    },
    {
      "component": 2,
      "x": 1059.6868,
      "y": 878.9369
    },
    {
      "component": 2,
      "x": 1064.3591,
      "y": 880.48206
    },
    {
      "component": 2,
      "x": 1069.0415,
      "y": 882.0599
    },
    {
      "component": 2,
      "x": 1073.9194,
      "y": 883.8393
    },
    {
      "component": 2,
      "x": 1078.5568,
      "y": 885.71796
    },
    {
      "component": 2,
      "x": 1082.9531,
      "y": 887.6958
    },
    {
      "component": 2,
      "x": 1087.4945,
      "y": 889.9217
    },
    {
      "component": 2,
      "x": 1091.8903,
      "y": 892.15216
    },
    {
      "component": 2,
      "x": 1096.293,
      "y": 894.48236
    },
    {
      "component": 2,
      "x": 1100.9552,
      "y": 896.931
    },
    {
      "component": 2,
      "x": 1105.3405,
      "y": 898.96234
    },
    {
      "component": 2,
      "x": 1109.9248,
      "y": 901.11224
    },
    {
      "component": 2,
      "x": 1113.8181,
      "y": 903.99164
    },
    {
      "component": 2,
      "x": 1117.3678,
      "y": 907.4835
    },
    {
      "component": 2,
      "x": 1121.7981,
      "y": 909.7103
    },
    {
      "component": 3,
      "x": 1121.0,
      "y": 537.0
    },
    {
      "component": 3,
      "x": 1122.0447,
      "y": 532.5755
    },
    {
      "component": 3,
      "x": 1123.3401,
      "y": 527.3656
    },
    {
      "component": 3,
      "x": 1124.9683,
      "y": 522.55304
    },
    {
      "component": 3,
      "x": 1126.8916,
      "y": 518.04926
    },
    {
      "component": 3,
      "x": 1129.1833,
      "y": 513.5018
    },
    {
      "component": 3,
      "x": 1131.5564,
      "y": 509.1692
    },
    {
      "component": 3,
      "x": 1134.0557,
      "y": 504.846
    },
    {
      "component": 3,
      "x": 1136.681,
      "y": 500.53223
    },
    {
      "component": 3,
      "x": 1139.3446,
      "y": 496.3908
    },
    {
      "component": 3,
      "x": 1142.216,
      "y": 492.29068
    },
    {
      "component": 3,
      "x": 1145.2308,
      "y": 488.29715
    },
    {
      "component": 3,
      "x": 1148.3418,
      "y": 484.42456
    },
    {
      "component": 3,
      "x": 1151.6937,
      "y": 480.46783
    },
    {
      "component": 3,
      "x": 1155.0776,
      "y": 476.62503
    },
    {
      "component": 3,
      "x": 1158.4758,
      "y": 472.8971
    },
    {
      "component": 3,
      "x": 1161.8883,
      "y": 469.28403
    },
    {
      "component": 3,
      "x": 1165.315,
      "y": 465.78583
    },
    {
      "component": 3,
      "x": 1168.797,
      "y": 462.36383
    },
    {
      "component": 3,
      "x": 1172.3914,
      "y": 458.97012
    },
    {
      "component": 3,
      "x": 1176.0867,
      "y": 455.6169
    },
    {
      "component": 3,
      "x": 1179.8828,
      "y": 452.3042
    },
    {
      "component": 3,
      "x": 1183.7799,
      "y": 449.03198
    },
    {
      "component": 3,
      "x": 1187.7007,
      "y": 445.8268
    },
    {
      "component": 3,
      "x": 1191.6178,
      "y": 442.67346
    },
    {
      "component": 3,
      "x": 1195.5312,
      "y": 439.57172
    },
    {
      "component": 3,
      "x": 1199.441,
      "y": 436.5216
    },
    {
      "component": 3,
      "x": 1203.4421,
      "y": 433.44373
    },
    {
      "component": 3,
      "x": 1207.5168,
      "y": 430.27985
    },
    {
      "component": 3,
      "x": 1211.4695,
      "y": 427.1608
    },
    {
      "component": 3,
      "x": 1215.2999,
      "y": 424.0866
    },
    {
      "component": 3,
      "x": 1219.0321,
      "y": 421.03763
    },
    {
      "component": 3,
      "x": 1222.9355,
      "y": 417.73965
    },
    {
      "component": 3,
      "x": 1226.6042,
      "y": 414.4815
    },
    {
      "component": 3,
      "x": 1230.304,
      "y": 410.99716
    },
    {
      "component": 3,
      "x": 1233.8707,
      "y": 407.40265
    },
    {
      "component": 3,
      "x": 1237.4656,
      "y": 403.6158
    },
    {
      "component": 3,
      "x": 1240.7344,
      "y": 400.01947
    },
    {
      "component": 3,
      "x": 1243.9637,
      "y": 396.26215
    },
    {
      "component": 3,
      "x": 1247.1301,
      "y": 392.2062
    },
    {
      "component": 3,
      "x": 1249.7664,
      "y": 388.34592
    },
    {
      "component": 3,
      "x": 1252.6965,
      "y": 384.2588
    },
    {
      "component": 3,
      "x": 1256.2762,
      "y": 380.57727
    },
    {
      "component": 3,
      "x": 1259.4596,
      "y": 378.27936
    },
    {
      "component": 3,
      "x": 1262.9509,
      "y": 381.87378
    },
    {
      "component": 3,
      "x": 1265.7432,
      "y": 385.98376
    },
    {
      "component": 3,
      "x": 1268.7338,
      "y": 390.0945
    },
    {
      "component": 3,
      "x": 1271.5323,
      "y": 394.18866
    },
    {
      "component": 3,
      "x": 1274.28,
      "y": 398.58957
    },
    {
      "component": 3,
      "x": 1277.0533,
      "y": 402.74194
    },
    {
      "component": 3,
      "x": 1279.8348,
      "y": 406.63428
    },
    {
      "component": 3,
      "x": 1282.6075,
      "y": 410.88553
    },
    {
      "component": 3,
      "x": 1285.5123,
      "y": 415.3485
    },
    {
      "component": 3,
      "x": 1288.4935,
      "y": 419.0418
    },
    {
      "component": 3,
      "x": 1291.5535,
      "y": 423.01382
    },
    {
      "component": 3,
      "x": 1294.1576,
      "y": 427.3532
    },
    {
      "component": 3,
      "x": 1296.4249,
      "y": 431.88577
    },
    {
      "component": 3,
      "x": 1298.9523,
      "y": 435.95737
    },
    {
      "component": 3,
      "x": 1301.5913,
      "y": 440.2136
    },
    {
      "component": 3,
      "x": 1303.9783,
      "y": 444.71478
    },
    {
      "component": 3,
      "x": 1305.9977,
      "y": 448.98172
    },
    {
      "component": 3,
      "x": 1307.4126,
      "y": 454.07916
    },
    {
      "component": 3,
      "x": 1308.8136,
      "y": 458.98532
    },
    {
      "component": 3,
      "x": 1310.5928,
      "y": 463.412
    },
    {
      "component": 3,
      "x": 1312.0944,
      "y": 468.26804
    },
    {
      "component": 3,
      "x": 1313.5077,
      "y": 473.20596
    },
    {
      "component": 3,
      "x": 1315.3176,
      "y": 477.7489
    },
    {
      "component": 3,
      "x": 1317.3496,
      "y": 482.3196
    },
    {
      "component": 3,
      "x": 1319.4008,
      "y": 486.71872
    },
    {
      "component": 3,
      "x": 1321.6726,
      "y": 491.34528
    },
    {
      "component": 3,
      "x": 1323.9098,
      "y": 495.8197
    },
    {
      "component": 3,
      "x": 1326.1838,
      "y": 500.31232
    },
    {
      "component": 3,
      "x": 1328.7688,
      "y": 504.60034
    },
    {
      "component": 3,
      "x": 1331.5605,
      "y": 508.37894
    },
    {
      "component": 3,
      "x": 1334.8224,
      "y": 512.27344
    },
    {
      "component": 3,
      "x": 1338.4457,
      "y": 516.40137
    },
    {
      "component": 3,
      "x": 1341.4291,
      "y": 520.2389
    },
    {
      "component": 3,
      "x": 1344.5132,
      "y": 524.30145
    },
    {
      "component": 3,
      "x": 1348.0734,
      "y": 527.4562
    },
    {
      "component": 3,
      "x": 1351.5753,
      "y": 531.1136
    },
    {
      "component": 3,
      "x": 1354.4233,
      "y": 535.0981
    },
    {
      "component": 3,
      "x": 1357.3208,
      "y": 539.0814
    },
    {
      "component": 3,
      "x": 1359.867,
      "y": 543.51624
    },
    {
      "component": 3,
      "x": 1361.8157,
      "y": 547.7613
    },
    {
      "component": 3,
      "x": 1363.9934,
      "y": 552.63275
    },
    {
      "component": 3,
      "x": 1366.006,
      "y": 557.20154
    },
    {
      "component": 3,
      "x": 1367.9879,
      "y": 561.76
    },
    {
      "component": 3,
      "x": 1369.9093,
      "y": 566.3296
    },
    {
      "component": 3,
      "x": 1371.7839,
      "y": 570.9692
    },
    {
      "component": 3,
      "x": 1373.4784,
      "y": 575.48785
    },
    {
      "component": 3,
      "x": 1375.1726,
      "y": 580.40247
    },
    {
      "component": 3,
      "x": 1376.5679,
      "y": 585.0933
    },
    {
      "component": 3,
      "x": 1377.6334,
      "y": 589.9755
    },
    {
      "component": 3,
      "x": 1378.4053,
      "y": 595.1701
    },
    {
      "component": 3,
      "x": 1379.1035,
      "y": 600.3983
    },
    {
      "component": 3,
      "x": 1379.8337,
      "y": 605.2196
    },
    {
      "component": 3,
      "x": 1380.6293,
      "y": 609.9083
    },
    {
      "component": 3,
      "x": 1381.4657,
      "y": 614.82404
    },
    {
      "component": 3,
      "x": 1382.3044,
      "y": 619.82556
    },
    {
      "component": 3,
      "x": 1383.1687,
      "y": 624.87335
    },
    {
      "component": 3,
      "x": 1384.0336,
      "y": 629.698
    },
    {
      "component": 3,
      "x": 1384.9274,
      "y": 634.80536
    },
    {
      "component": 3,
      "x": 1385.6036,
      "y": 639.61707
    },
    {
      "component": 3,
      "x": 1386.1576,
      "y": 644.6458
    },
    {
      "component": 3,
      "x": 1386.66,
      "y": 649.4638
    },
    {
      "component": 3,
      "x": 1387.498,
      "y": 654.3739
    },
    {
      "component": 3,
      "x": 1388.738,
      "y": 659.2406
    },
    {
      "component": 3,
      "x": 1389.5507,
      "y": 664.18646
    },
    {
      "component": 3,
      "x": 1390.304,
      "y": 669.2763
    },
    {
      "component": 3,
      "x": 1391.644,
      "y": 673.9271
    },
    {
      "component": 3,
      "x": 1393.0721,
      "y": 678.73975
    },
    {
      "component": 3,
      "x": 1394.203,
      "y": 683.5507
    },
    {
      "component": 3,
      "x": 1394.9579,
      "y": 688.75104
    },
    {
      "component": 3,
      "x": 1395.6656,
      "y": 693.5633
    },
    {
      "component": 3,
      "x": 1396.1255,
      "y": 698.57874
    },
    {
      "component": 3,
      "x": 1396.5172,
      "y": 703.4983
    },
    {
      "component": 3,
      "x": 1394.7687,
      "y": 706.6759
    },
    {
      "component": 3,
      "x": 1390.4432,
      "y": 709.05023
    },
    {
      "component": 3,
      "x": 1386.2622,
      "y": 711.7605
    },
    {
      "component": 3,
      "x": 1382.2358,
      "y": 714.7682
    },
    {
      "component": 3,
      "x": 1378.1843,
      "y": 717.60645
    },
    {
      "component": 3,
      "x": 1374.9692,
      "y": 720.7314
    },
    {
      "component": 3,
      "x": 1371.663,
      "y": 724.33704
    },
    {
      "component": 3,
      "x": 1368.0344,
      "y": 727.9628
    },
    {
      "component": 3,
      "x": 1363.9125,
      "y": 730.84467
    },
    {
      "component": 3,
      "x": 1359.7725,
      "y": 733.5802
    },
    {
      "component": 3,
      "x": 1356.0531,
      "y": 736.7121
    },
    {
      "component": 3,
      "x": 1352.292,
      "y": 739.96454
    },
    {
      "component": 3,
      "x": 1348.5984,
      "y": 743.19006
    },
    {
      "component": 3,
      "x": 1344.4198,
      "y": 746.82666
    },
    {
      "component": 3,
      "x": 1340.5066,
      "y": 749.9656
    },
    {
      "component": 3,
      "x": 1336.676,
      "y": 752.7884
    },
    {
      "component": 3,
      "x": 1332.8778,
      "y": 756.0416
    },
    {
      "component": 3,
      "x": 1329.1749,
      "y": 759.4957
    },
    {
      "component": 3,
      "x": 1325.1945,
      "y": 762.9123
    },
    {
      "component": 3,
      "x": 1321.8275,
      "y": 766.0753
    },
    {
      "component": 3,
      "x": 1318.373,
      "y": 769.6262
    },
    {
      "component": 3,
      "x": 1315.127,
      "y": 772.87305
    },
    {
      "component": 3,
      "x": 1311.2192,
      "y": 776.7808
    },
    {
      "component": 3,
      "x": 1307.8221,
      "y": 780.0989
    },
    {
      "component": 3,
      "x": 1304.1152,
      "y": 783.57153
    },
    {
      "component": 3,
      "x": 1300.3771,
      "y": 786.9751
    },
    {
      "component": 3,
      "x": 1296.8026,
      "y": 790.32135
    },
    {
      "component": 3,
      "x": 1293.1364,
      "y": 793.8758
    },
    {
      "component": 3,
      "x": 1289.5862,
      "y": 797.41077
    },
    {
      "component": 3,
      "x": 1286.1025,
      "y": 800.87305
    },
    {
      "component": 3,
      "x": 1282.5035,
      "y": 804.4302
    },
    {
      "component": 3,
      "x": 1278.8939,
      "y": 807.9781
    },
    {
      "component": 3,
      "x": 1275.4321,
      "y": 811.3349
    },
    {
      "component": 3,
      "x": 1271.8229,
      "y": 814.78094
    },
    {
      "component": 3,
      "x": 1268.0659,
      "y": 818.31635
    },
    {
      "component": 3,
      "x": 1264.4305,
      "y": 821.6923
    },
    {
      "component": 3,
      "x": 1260.729,
      "y": 825.0894
    },
    {
      "component": 3,
      "x": 1257.0297,
      "y": 828.45105
    },
    {
      "component": 3,
      "x": 1253.3423,
      "y": 831.77435
    },
    {
      "component": 3,
      "x": 1249.4939,
      "y": 835.2188
    },
    {
      "component": 3,
      "x": 1245.7593,
      "y": 838.58386
    },
    {
      "component": 3,
      "x": 1242.0588,
      "y": 841.9641
    },
    {
      "component": 3,
      "x": 1238.3926,
      "y": 845.3596
    },
    {
      "component": 3,
      "x": 1234.7605,
      "y": 848.77026
    },
    {
      "component": 3,
      "x": 1231.1196,
      "y": 852.2368
    },
    {
      "component": 3,
      "x": 1227.3949,
      "y": 855.81995
    },
    {
      "component": 3,
      "x": 1223.761,
      "y": 859.348
    },
    {
      "component": 3,
      "x": 1220.2177,
      "y": 862.821
    },
    {
      "component": 3,
      "x": 1216.7651,
      "y": 866.23883
    },
    {
      "component": 3,
      "x": 1213.209,
      "y": 869.7834
    },
    {
      "component": 3,
      "x": 1209.5466,
      "y": 873.38855
    },
    {
      "component": 3,
      "x": 1205.9468,
      "y": 876.8756
    },
    {
      "component": 3,
      "x": 1202.4094,
      "y": 880.24457
    },
    {
      "component": 3,
      "x": 1198.8304,
      "y": 883.5972
    },
    {
      "component": 3,
      "x": 1195.0942,
      "y": 887.1261
    },
    {
      "component": 3,
      "x": 1191.4786,
      "y": 890.60236
    },
    {
      "component": 3,
      "x": 1187.9839,
      "y": 894.02606
    },
    {
      "component": 3,
      "x": 1184.4392,
      "y": 897.5716
    },
    {
      "component": 3,
      "x": 1180.8572,
      "y": 901.25256
    },
    {
      "component": 3,
      "x": 1177.4546,
      "y": 904.8571
    },
    {
      "component": 3,
      "x": 1174.2147,
      "y": 908.4039
    },
    {
      "component": 3,
      "x": 1170.5492,
      "y": 912.4915
    },
    {
      "component": 3,
      "x": 1167.268,
      "y": 916.1673
    },
    {
      "component": 3,
      "x": 1164.1736,
      "y": 919.661
    },
    {
      "component": 3,
      "x": 1160.8574,
      "y": 923.605
    },
    {
      "component": 3,
      "x": 1157.8788,
      "y": 927.462
    },
    {
      "component": 3,
      "x": 1154.9862,
      "y": 931.11334
    },
    {
      "component": 3,
      "x": 1152.7831,
      "y": 935.8991
    },
    {
      "component": 3,
      "x": 1152.0,
      "y": 940.7715
    },
    {
      "component": 4,
      "x": 1068.0,
      "y": 572.0
    },
    {
      "component": 4,
      "x": 1068.0,
      "y": 576.72345
    },
    {
      "component": 4,
      "x": 1068.1151,
      "y": 581.9732
    },
    {
      "component": 4,
      "x": 1068.436,
      "y": 586.97394
    },
    {
      "component": 4,
      "x": 1068.8378,
      "y": 591.86414
    },
    {
      "component": 4,
      "x": 1069.2931,
      "y": 596.7819
    },
    {
      "component": 4,
      "x": 1069.8024,
      "y": 601.88544
    },
    {
      "component": 4,
      "x": 1070.309,
      "y": 606.72754
    },
    {
      "component": 4,
      "x": 1070.8477,
      "y": 611.6899
    },
    {
      "component": 4,
      "x": 1071.4185,
      "y": 616.7724
    },
    {
      "component": 4,
      "x": 1071.9884,
      "y": 621.69476
    },
    {
      "component": 4,
      "x": 1072.5698,
      "y": 626.58215
    },
    {
      "component": 4,
      "x": 1073.1785,
      "y": 631.57135
    },
    {
      "component": 4,
      "x": 1073.8143,
      "y": 636.66235
    },
    {
      "component": 4,
      "x": 1074.4791,
      "y": 641.7788
    },
    {
      "component": 4,
      "x": 1075.1836,
      "y": 646.8418
    },
    {
      "component": 4,
      "x": 1075.9285,
      "y": 651.85376
    },
    {
      "component": 4,
      "x": 1076.7139,
      "y": 656.81476
    },
    {
      "component": 4,
      "x": 1077.5397,
      "y": 661.7248
    },
    {
      "component": 4,
      "x": 1078.406,
      "y": 666.5838
    },
    {
      "component": 4,
      "x": 1079.3127,
      "y": 671.39185
    },
    {
      "component": 4,
      "x": 1080.2687,
      "y": 676.19385
    },
    {
      "component": 4,
      "x": 1081.2972,
      "y": 681.2502
    },
    {
      "component": 4,
      "x": 1082.3176,
      "y": 686.25305
    },
    {
      "component": 4,
      "x": 1083.3298,
      "y": 691.20245
    },
    {
      "component": 4,
      "x": 1084.3339,
      "y": 696.0983
    },
    {
      "component": 4,
      "x": 1085.3296,
      "y": 700.9408
    },
    {
      "component": 4,
      "x": 1086.3171,
      "y": 705.72974
    },
    {
      "component": 4,
      "x": 1087.2965,
      "y": 710.4652
    },
    {
      "component": 4,
      "x": 1088.2838,
      "y": 715.2313
    },
    {
      "component": 4,
      "x": 1089.2913,
      "y": 720.0951
    },
    {
      "component": 4,
      "x": 1090.3187,
      "y": 725.05585
    },
    {
      "component": 4,
      "x": 1091.3397,
      "y": 729.9855
    },
    {
      "component": 4,
      "x": 1092.3356,
      "y": 734.79407
    },
    {
      "component": 4,
      "x": 1093.349,
      "y": 739.68726
    },
    {
      "component": 4,
      "x": 1094.3799,
      "y": 744.6651
    },
    {
      "component": 4,
      "x": 1095.4126,
      "y": 749.66504
    },
    {
      "component": 4,
      "x": 1096.4209,
      "y": 754.6205
    },
    {
      "component": 4,
      "x": 1097.4086,
      "y": 759.5596
    },
    {
      "component": 4,
      "x": 1098.3759,
      "y": 764.4823
    },
    {
      "component": 4,
      "x": 1099.3226,
      "y": 769.3886
    },
    {
      "component": 4,
      "x": 1100.249,
      "y": 774.2785
    },
    {
      "component": 4,
      "x": 1101.1548,
      "y": 779.15204
    },
    {
      "component": 4,
      "x": 1102.0402,
      "y": 784.0092
    },
    {
      "component": 4,
      "x": 1102.9293,
      "y": 788.97345
    },
    {
      "component": 4,
      "x": 1103.8114,
      "y": 793.9548
    },
    {
      "component": 4,
      "x": 1104.6796,
      "y": 798.9146
    },
    {
      "component": 4,
      "x": 1105.5338,
      "y": 803.853
    },
    {
      "component": 4,
      "x": 1106.3741,
      "y": 808.77
    },
    {
      "component": 4,
      "x": 1107.2006,
      "y": 813.6656
    },
    {
      "component": 4,
      "x": 1108.0131,
      "y": 818.53973
    },
    {
      "component": 4,
      "x": 1108.823,
      "y": 823.45996
    },
    {
      "component": 4,
      "x": 1109.6498,
      "y": 828.5204
    },
    {
      "component": 4,
      "x": 1110.4524,
      "y": 833.4605
    },
    {
      "component": 4,
      "x": 1111.231,
      "y": 838.2804
    },
    {
      "component": 4,
      "x": 1112.0339,
      "y": 843.28314
    },
    {
      "component": 4,
      "x": 1112.8309,
      "y": 848.2835
    },
    {
      "component": 4,
      "x": 1113.5989,
      "y": 853.13965
    },
    {
      "component": 4,
      "x": 1114.3798,
      "y": 858.1244
    },
    {
      "component": 4,
      "x": 1115.1603,
      "y": 863.2009
    },
    {
      "component": 4,
      "x": 1115.8804,
      "y": 867.99744
    },
    {
      "component": 4,
      "x": 1116.613,
      "y": 873.0218
    },
    {
      "component": 4,
      "x": 1117.3137,
      "y": 878.01154
    },
    {
      "component": 4,
      "x": 1117.9429,
      "y": 882.69476
    },
    {
      "component": 4,
      "x": 1118.636,
      "y": 887.5857
    },
    {
      "component": 4,
      "x": 1119.4012,
      "y": 892.5068
    },
    {
      "component": 4,
      "x": 1120.2385,
      "y": 897.45807
    },
    {
      "component": 4,
      "x": 1121.148,
      "y": 902.4395
    },
    {
      "component": 4,
      "x": 1122.1277,
      "y": 907.49414
    },
    {
      "component": 4,
      "x": 1123.1035,
      "y": 912.33057
    },
    {
      "component": 4,
      "x": 1124.1483,
      "y": 917.285
    },
    {
      "component": 4,
      "x": 1125.2134,
      "y": 922.089
    },
    {
      "component": 4,
      "x": 1126.3129,
      "y": 927.1002
    },
    {
      "component": 4,
      "x": 1127.2466,
      "y": 932.0789
    },
    {
      "component": 4,
      "x": 1127.9856,
      "y": 936.9171
    },
    {
      "component": 4,
      "x": 1128.5907,
      "y": 941.8459
    },
    {
      "component": 4,
      "x": 1129.3164,
      "y": 946.7123
    },
    {
      "component": 4,
      "x": 1130.3037,
      "y": 951.6903
    },
    {
      "component": 4,
      "x": 1131.5161,
      "y": 956.7274
    },
    {
      "component": 4,
      "x": 1132.0469,
      "y": 961.4045
    },
    {
      "component": 5,
      "x": 1136.0,
      "y": 554.0
    },
    {
      "component": 5,
      "x": 1135.5598,
      "y": 558.83105
    },
    {
      "component": 5,
      "x": 1135.2837,
      "y": 563.82306
    },
    {
      "component": 5,
      "x": 1135.3485,
      "y": 568.78766
    },
    {
      "component": 5,
      "x": 1135.6405,
      "y": 573.92053
    },
    {
      "component": 5,
      "x": 1135.904,
      "y": 578.60504
    },
    {
      "component": 5,
      "x": 1136.0653,
      "y": 583.53656
    },
    {
      "component": 5,
      "x": 1136.1241,
      "y": 588.71515
    },
    {
      "component": 5,
      "x": 1136.0914,
      "y": 593.8222
    },
    {
      "component": 5,
      "x": 1136.0522,
      "y": 598.56665
    },
    {
      "component": 5,
      "x": 1136.0239,
      "y": 603.49774
    },
    {
      "component": 5,
      "x": 1136.0066,
      "y": 608.6153
    },
    {
      "component": 5,
      "x": 1136.0,
      "y": 613.91943
    },
    {
      "component": 5,
      "x": 1136.0,
      "y": 618.8057
    },
    {
      "component": 5,
      "x": 1136.0,
      "y": 623.71387
    },
    {
      "component": 5,
      "x": 1136.0,
      "y": 628.7043
    },
    {
      "component": 5,
      "x": 1136.0,
      "y": 633.77704
    },
    {
      "component": 5,
      "x": 1136.0,
      "y": 638.9321
    },
    {
      "component": 5,
      "x": 1136.0303,
      "y": 643.9702
    },
    {
      "component": 5,
      "x": 1136.1407,
      "y": 648.9755
    },
    {
      "component": 5,
      "x": 1136.3323,
      "y": 653.973
    },
    {
      "component": 5,
      "x": 1136.6045,
      "y": 658.96265
    },
    {
      "component": 5,
      "x": 1136.9578,
      "y": 663.9444
    },
    {
      "component": 5,
      "x": 1137.3696,
      "y": 668.8753
    },
    {
      "component": 5,
      "x": 1137.7772,
      "y": 673.80804
    },
    {
      "component": 5,
      "x": 1138.1771,
      "y": 678.77466
    },
    {
      "component": 5,
      "x": 1138.5696,
      "y": 683.7752
    },
    {
      "component": 5,
      "x": 1138.9543,
      "y": 688.8097
    },
    {
      "component": 5,
      "x": 1139.337,
      "y": 693.9098
    },
    {
      "component": 5,
      "x": 1139.7582,
      "y": 699.03296
    },
    {
      "component": 5,
      "x": 1140.2238,
      "y": 704.07263
    },
    {
      "component": 5,
      "x": 1140.7338,
      "y": 709.0288
    },
    {
      "component": 5,
      "x": 1141.2883,
      "y": 713.9015
    },
    {
      "component": 5,
      "x": 1141.8914,
      "y": 718.72363
    },
    {
      "component": 5,
      "x": 1142.5609,
      "y": 723.72003
    },
    {
      "component": 5,
      "x": 1143.2638,
      "y": 728.68915
    },
    {
      "component": 5,
      "x": 1144.0001,
      "y": 733.63104
    },
    {
      "component": 5,
      "x": 1144.7698,
      "y": 738.54565
    },
    {
      "component": 5,
      "x": 1145.563,
      "y": 743.3902
    },
    {
      "component": 5,
      "x": 1146.2797,
      "y": 748.12354
    },
    {
      "component": 5,
      "x": 1146.9137,
      "y": 752.98126
    },
    {
      "component": 5,
      "x": 1147.4647,
      "y": 757.96326
    },
    {
      "component": 5,
      "x": 1147.933,
      "y": 763.06964
    },
    {
      "component": 5,
      "x": 1148.3182,
      "y": 768.29663
    },
    {
      "component": 5,
      "x": 1148.696,
      "y": 773.37805
    },
    {
      "component": 5,
      "x": 1149.1584,
      "y": 778.4072
    },
    {
      "component": 5,
      "x": 1149.7053,
      "y": 783.3841
    },
    {
      "component": 5,
      "x": 1150.3369,
      "y": 788.30865
    },
    {
      "component": 5,
      "x": 1151.053,
      "y": 793.18097
    },
    {
      "component": 5,
      "x": 1151.8502,
      "y": 798.15704
    },
    {
      "component": 5,
      "x": 1152.6211,
      "y": 803.1685
    },
    {
      "component": 5,
      "x": 1153.345,
      "y": 808.136
    },
    {
      "component": 5,
      "x": 1154.0217,
      "y": 813.0595
    },
    {
      "component": 5,
      "x": 1154.6516,
      "y": 817.9391
    },
    {
      "component": 5,
      "x": 1155.2837,
      "y": 823.0434
    },
    {
      "component": 5,
      "x": 1155.9828,
      "y": 828.218
    },
    {
      "component": 5,
      "x": 1156.7295,
      "y": 833.2077
    },
    {
      "component": 5,
      "x": 1157.5239,
      "y": 838.01245
    },
    {
      "component": 5,
      "x": 1158.366,
      "y": 842.6323
    },
    {
      "component": 5,
      "x": 1159.3079,
      "y": 847.70074
    },
    {
      "component": 5,
      "x": 1160.1172,
      "y": 852.46625
    },
    {
      "component": 5,
      "x": 1160.8801,
      "y": 857.5715
    },
    {
      "component": 5,
      "x": 1161.4902,
      "y": 862.4847
    },
    {
      "component": 5,
      "x": 1162.1272,
      "y": 867.67194
    },
    {
      "component": 5,
      "x": 1162.7645,
      "y": 872.49664
    },
    {
      "component": 5,
      "x": 1163.4816,
      "y": 877.43567
    },
    {
      "component": 5,
      "x": 1164.348,
      "y": 882.4443
    },
    {
      "component": 5,
      "x": 1165.336,
      "y": 887.1521
    },
    {
      "component": 5,
      "x": 1166.3351,
      "y": 892.09564
    },
    {
      "component": 6,
      "x": 1223.0,
      "y": 608.0
    },
    {
      "component": 6,
      "x": 1226.4982,
      "y": 605.1432
    },
    {
      "component": 6,
      "x": 1230.7632,
      "y": 601.64703
    },
    {
      "component": 6,
      "x": 1234.5978,
      "y": 598.391
    },
    {
      "component": 6,
      "x": 1238.3252,
      "y": 595.09125
    },
    {
      "component": 6,
      "x": 1242.0186,
      "y": 591.7231
    },
    {
      "component": 6,
      "x": 1245.8892,
      "y": 588.4986
    },
    {
      "component": 6,
      "x": 1249.8997,
      "y": 585.55286
    },
    {
      "component": 6,
      "x": 1254.03,
      "y": 582.8207
    },
    {
      "component": 6,
      "x": 1258.0522,
      "y": 579.88153
    },
    {
      "component": 6,
      "x": 1261.9067,
      "y": 576.6608
    },
    {
      "component": 6,
      "x": 1265.644,
      "y": 573.1967
    },
    {
      "component": 6,
      "x": 1269.3927,
      "y": 569.82465
    },
    {
      "component": 6,
      "x": 1273.1493,
      "y": 566.6152
    },
    {
      "component": 6,
      "x": 1277.1411,
      "y": 563.33417
    },
    {
      "component": 6,
      "x": 1281.0162,
      "y": 560.09766
    },
    {
      "component": 6,
      "x": 1284.6656,
      "y": 556.9756
    },
    {
      "component": 6,
      "x": 1288.3676,
      "y": 553.5276
    },
    {
      "component": 7,
      "x": 1273.0,
      "y": 656.0
    },
    {
      "component": 7,
      "x": 1276.1821,
      "y": 652.1836
    },
    {
      "component": 7,
      "x": 1279.6781,
      "y": 648.576
    },
    {
      "component": 7,
      "x": 1283.4031,
      "y": 645.3714
    },
    {
      "component": 7,
      "x": 1287.7188,
      "y": 642.03406
    },
    {
      "component": 7,
      "x": 1291.7548,
      "y": 639.1027
    },
    {
      "component": 7,
      "x": 1295.767,
      "y": 636.4348
    },
    {
      "component": 7,
      "x": 1300.2648,
      "y": 634.0528
    },
    {
      "component": 7,
      "x": 1304.873,
      "y": 632.3284
    },
    {
      "component": 8,
      "x": 1274.0,
      "y": 739.0
    },
    {
      "component": 8,
      "x": 1276.8872,
      "y": 735.1504
    },
    {
      "component": 8,
      "x": 1279.8923,
      "y": 731.1436
    },
    {
      "component": 8,
      "x": 1283.1277,
      "y": 726.8055
    },
    {
      "component": 8,
      "x": 1286.0538,
      "y": 722.75085
    },
    {
      "component": 8,
      "x": 1288.879,
      "y": 718.6482
    },
    {
      "component": 8,
      "x": 1291.5565,
      "y": 714.4796
    },
    {
      "component": 8,
      "x": 1294.029,
      "y": 710.32635
    },
    {
      "component": 9,
      "x": 1129.0,
      "y": 487.0
    },
    {
      "component": 9,
      "x": 1132.8839,
      "y": 484.4107
    },
    {
      "component": 9,
      "x": 1137.7535,
      "y": 481.18042
    },
    {
      "component": 9,
      "x": 1141.8087,
      "y": 478.553
    },
    {
      "component": 9,
      "x": 1145.5419,
      "y": 475.96478
    },
    {
      "component": 9,
      "x": 1149.1467,
      "y": 472.5288
    },
    {
      "component": 9,
      "x": 1152.4666,
      "y": 468.73175
    },
    {
      "component": 9,
      "x": 1155.7137,
      "y": 464.9852
    },
    {
      "component": 9,
      "x": 1159.0883,
      "y": 461.1344
    },
    {
      "component": 9,
      "x": 1162.1987,
      "y": 457.71057
    },
    {
      "component": 9,
      "x": 1165.6432,
      "y": 454.14767
    },
    {
      "component": 9,
      "x": 1169.4581,
      "y": 450.40472
    },
    {
      "component": 9,
      "x": 1172.8792,
      "y": 447.13126
    },
    {
      "component": 9,
      "x": 1176.3462,
      "y": 443.76816
    },
    {
      "component": 9,
      "x": 1179.9912,
      "y": 440.1871
    },
    {
      "component": 9,
      "x": 1183.8143,
      "y": 436.38803
    },
    {
      "component": 9,
      "x": 1187.3622,
      "y": 432.94083
    },
    {
      "component": 9,
      "x": 1191.0872,
      "y": 429.53687
    },
    {
      "component": 9,
      "x": 1194.8429,
      "y": 426.29495
    },
    {
      "component": 9,
      "x": 1198.716,
      "y": 423.12408
    },
    {
      "component": 9,
      "x": 1202.784,
      "y": 419.95047
    },
    {
      "component": 9,
      "x": 1206.8933,
      "y": 416.82028
    },
    {
      "component": 9,
      "x": 1210.9382,
      "y": 413.7945
    },
    {
      "component": 9,
      "x": 1214.9192,
      "y": 410.87308
    },
    {
      "component": 9,
      "x": 1218.8359,
      "y": 408.05603
    },
    {
      "component": 9,
      "x": 1222.9375,
      "y": 405.11877
    },
    {
      "component": 9,
      "x": 1227.0087,
      "y": 402.08847
    },
    {
      "component": 9,
      "x": 1230.9507,
      "y": 399.0289
    },
    {
      "component": 9,
      "x": 1234.7633,
      "y": 395.93997
    },
    {
      "component": 9,
      "x": 1238.5298,
      "y": 392.76892
    },
    {
      "component": 9,
      "x": 1242.3461,
      "y": 389.53857
    },
    {
      "component": 10,
      "x": 1104.0,
      "y": 525.0
    },
    {
      "component": 10,
      "x": 1106.148,
      "y": 521.04346
    },
    {
      "component": 10,
      "x": 1108.8237,
      "y": 516.12427
    },
    {
      "component": 10,
      "x": 1111.309,
      "y": 511.65317
    },
    {
      "component": 10,
      "x": 1113.7515,
      "y": 507.3785
    },
    {
      "component": 10,
      "x": 1116.1516,
      "y": 503.28183
    },
    {
      "component": 10,
      "x": 1118.6829,
      "y": 498.89777
    },
    {
      "component": 10,
      "x": 1121.098,
      "y": 494.63135
    },
    {
      "component": 10,
      "x": 1123.6028,
      "y": 490.13806
    },
    {
      "component": 10,
      "x": 1126.0825,
      "y": 485.82916
    },
    {
      "component": 10,
      "x": 1128.6919,
      "y": 481.5729
    },
    {
      "component": 10,
      "x": 1131.4308,
      "y": 477.36935
    },
    {
      "component": 10,
      "x": 1134.2592,
      "y": 473.27835
    },
    {
      "component": 10,
      "x": 1137.2031,
      "y": 469.30923
    },
    {
      "component": 10,
      "x": 1140.3502,
      "y": 465.3391
    },
    {
      "component": 10,
      "x": 1143.5157,
      "y": 461.56754
    },
    {
      "component": 10,
      "x": 1146.9058,
      "y": 457.72525
    },
    {
      "component": 10,
      "x": 1150.1447,
      "y": 454.10324
    },
    {
      "component": 10,
      "x": 1153.4015,
      "y": 450.398
    },
    {
      "component": 10,
      "x": 1156.6763,
      "y": 446.60956
    },
    {
      "component": 10,
      "x": 1159.969,
      "y": 442.73785
    },
    {
      "component": 10,
      "x": 1163.2716,
      "y": 438.79456
    },
    {
      "component": 10,
      "x": 1166.5455,
      "y": 434.9049
    },
    {
      "component": 10,
      "x": 1169.8176,
      "y": 431.07645
    },
    {
      "component": 10,
      "x": 1173.088,
      "y": 427.3092
    },
    {
      "component": 10,
      "x": 1176.3567,
      "y": 423.60318
    },
    {
      "component": 10,
      "x": 1179.6488,
      "y": 419.93594
    },
    {
      "component": 10,
      "x": 1183.0638,
      "y": 416.2922
    },
    {
      "component": 10,
      "x": 1186.5742,
      "y": 412.7364
    },
    {
      "component": 10,
      "x": 1190.18,
      "y": 409.2685
    },
    {
      "component": 10,
      "x": 1193.8812,
      "y": 405.8885
    },
    {
      "component": 10,
      "x": 1197.605,
      "y": 402.64703
    },
    {
      "component": 10,
      "x": 1201.3429,
      "y": 399.47583
    },
    {
      "component": 10,
      "x": 1205.1647,
      "y": 396.30203
    },
    {
      "component": 10,
      "x": 1209.0703,
      "y": 393.1256
    },
    {
      "component": 10,
      "x": 1213.0598,
      "y": 389.94662
    },
    {
      "component": 10,
      "x": 1217.0522,
      "y": 386.81952
    },
    {
      "component": 10,
      "x": 1220.992,
      "y": 383.74072
    },
    {
      "component": 10,
      "x": 1224.9315,
      "y": 380.6619
    },
    {
      "component": 11,
      "x": 1114.0,
      "y": 509.0
    },
    {
      "component": 11,
      "x": 1112.8606,
      "y": 504.66165
    },
    {
      "component": 11,
      "x": 1111.462,
      "y": 499.24847
    },
    {
      "component": 11,
      "x": 1110.5015,
      "y": 494.36603
    },
    {
      "component": 11,
      "x": 1109.9666,
      "y": 489.35318
    },
    {
      "component": 11,
      "x": 1109.9573,
      "y": 484.36398
    },
    {
      "component": 11,
      "x": 1110.3304,
      "y": 479.30878
    },
    {
      "component": 11,
      "x": 1111.0397,
      "y": 474.46072
    },
    {
      "component": 11,
      "x": 1112.007,
      "y": 470.01688
    },
    {
      "component": 11,
      "x": 1113.3082,
      "y": 465.23544
    },
    {
      "component": 11,
      "x": 1114.9598,
      "y": 460.02625
    },
    {
      "component": 11,
      "x": 1116.738,
      "y": 455.4619
    },
    {
      "component": 11,
      "x": 1118.969,
      "y": 450.9278
    },
    {
      "component": 11,
      "x": 1121.4622,
      "y": 446.66113
    },
    {
      "component": 11,
      "x": 1124.2961,
      "y": 442.40408
    },
    {
      "component": 11,
      "x": 1127.1816,
      "y": 438.3503
    },
    {
      "component": 11,
      "x": 1130.1736,
      "y": 434.34998
    },
    {
      "component": 11,
      "x": 1133.2719,
      "y": 430.403
    },
    {
      "component": 11,
      "x": 1136.498,
      "y": 426.48608
    },
    {
      "component": 11,
      "x": 1139.8761,
      "y": 422.63043
    },
    {
      "component": 11,
      "x": 1143.3177,
      "y": 418.9683
    },
    {
      "component": 11,
      "x": 1146.8228,
      "y": 415.49963
    },
    {
      "component": 11,
      "x": 1150.447,
      "y": 412.17743
    },
    {
      "component": 11,
      "x": 1154.3107,
      "y": 408.9627
    },
    {
      "component": 11,
      "x": 1158.3088,
      "y": 405.99265
    },
    {
      "component": 11,
      "x": 1162.4946,
      "y": 403.25214
    },
    {
      "component": 11,
      "x": 1166.6384,
      "y": 400.80164
    },
    {
      "component": 11,
      "x": 1170.7507,
      "y": 398.206
    },
    {
      "component": 11,
      "x": 1174.9104,
      "y": 395.36835
    },
    {
      "component": 11,
      "x": 1179.1173,
      "y": 392.2888
    },
    {
      "component": 11,
      "x": 1183.1342,
      "y": 389.21912
    },
    {
      "component": 11,
      "x": 1187.1055,
      "y": 386.18124
    },
    {
      "component": 12,
      "x": 1121.0,
      "y": 523.0
    },
    {
      "component": 12,
      "x": 1119.9106,
      "y": 518.15607
    },
    {
      "component": 12,
      "x": 1119.0288,
      "y": 512.9067
    },
    {
      "component": 12,
      "x": 1118.9077,
      "y": 508.38974
    },
    {
      "component": 12,
      "x": 1119.4371,
      "y": 503.25858
    },
    {
      "component": 12,
      "x": 1120.1144,
      "y": 498.64197
    },
    {
      "component": 12,
      "x": 1120.987,
      "y": 493.4018
    },
    {
      "component": 12,
      "x": 1121.855,
      "y": 488.6474
    },
    {
      "component": 12,
      "x": 1122.8143,
      "y": 483.7886
    },
    {
      "component": 12,
      "x": 1123.8652,
      "y": 478.8254
    },
    {
      "component": 12,
      "x": 1125.0074,
      "y": 473.7578
    },
    {
      "component": 12,
      "x": 1126.0887,
      "y": 468.99524
    },
    {
      "component": 12,
      "x": 1127.1392,
      "y": 464.06638
    },
    {
      "component": 12,
      "x": 1128.1248,
      "y": 459.15256
    },
    {
      "component": 12,
      "x": 1129.0444,
      "y": 454.29865
    },
    {
      "component": 12,
      "x": 1129.9468,
      "y": 449.27
    },
    {
      "component": 12,
      "x": 1130.7826,
      "y": 444.31424
    },
    {
      "component": 12,
      "x": 1131.5477,
      "y": 439.3845
    },
    {
      "component": 12,
      "x": 1132.2491,
      "y": 434.4379
    },
    {
      "component": 12,
      "x": 1132.887,
      "y": 429.47443
    },
    {
      "component": 12,
      "x": 1133.461,
      "y": 424.49408
    },
    {
      "component": 12,
      "x": 1133.9783,
      "y": 419.46564
    },
    {
      "component": 12,
      "x": 1134.5524,
      "y": 414.40533
    },
    {
      "component": 12,
      "x": 1135.2194,
      "y": 409.5006
    },
    {
      "component": 12,
      "x": 1136.012,
      "y": 404.56235
    },
    {
      "component": 12,
      "x": 1136.9423,
      "y": 399.60852
    },
    {
      "component": 12,
      "x": 1137.9812,
      "y": 394.83658
    },
    {
      "component": 12,
      "x": 1139.1592,
      "y": 389.84784
    },
    {
      "component": 12,
      "x": 1140.3156,
      "y": 385.0517
    },
    {
      "component": 12,
      "x": 1141.5259,
      "y": 380.14545
    },
    {
      "component": 12,
      "x": 1142.7446,
      "y": 375.32996
    },
    {
      "component": 12,
      "x": 1144.1031,
      "y": 370.41815
    },
    {
      "component": 12,
      "x": 1145.838,
      "y": 365.81683
    },
    {
      "component": 12,
      "x": 1148.214,
      "y": 361.34448
    },
    {
      "component": 12,
      "x": 1151.1699,
      "y": 357.50296
    },
    {
      "component": 12,
      "x": 1154.791,
      "y": 354.06073
    },
    {
      "component": 12,
      "x": 1158.7958,
      "y": 351.14093
    },
    {
      "component": 12,
      "x": 1163.212,
      "y": 348.63678
    },
    {
      "component": 12,
      "x": 1167.6506,
      "y": 346.33493
    }
  ],
  "session_data": {
    "age": 58,
    "configuration": {
      "guide_lines": false,
      "items": [
        "Aereo",
        "Arcobaleno",
        "Baffi",
        "Balena",
        "Barca",
        "Bottiglia",
        "Busta",
        "Cacciavite",
        "Calice",
        "Calzino",
        "Candela",
        "Cane",
        "Chiave",
        "Chitarra",
        "Cigno",
        "Coccodrillo",
        "Cornice",
        "Corona",
        "Cuscino",
        "Faccia",
        "Fiammifero",
        "Fiocco",
        "Fiume",
        "Forchetta",
        "Fulmine",
        "Gatto",
        "Gelato",
        "Grattacielo",
        "Lampadina",
        "Lavatrice",
        "Libro",
        "Luna",
        "Macchina",
        "Mare",
        "Matita",
        "Montagna",
        "Nuvola",
        "Omino",
        "Orecchio",
        "Orologio",
        "Pesce",
        "Piede",
        "Pipistrello",
        "Pupazzo di neve",
        "Ragno",
        "Rossetto",
        "Ruota",
        "Sassofono",
        "Scarabocchio",
        "Scarpa",
        "Secchio",
        "Sirena",
        "Smile",
        "Sole",
        "Spada",
        "Stella",
        "T-shirt",
        "Tazza",
        "Teschio",
        "Torcia elettrica",
        "Uva"
      ],
      "repetitions": 1,
      "repetitions_label": "Ripetizioni",
      "title": "Devi disegnare: "
    },
    "date": "24.01.2019.23.53",
    "device_data": {
      "device_finger_print": "HUAWEI/WAS-LX1A/HWWAS-H:8.0.0/HUAWEIWAS-LX1A/377(C432):user/release-keys",
      "device_model": "WAS-LX1A",
      "heigth_pixels": 1080,
      "width_pixels": 1795,
      "xdpi": 422.03,
      "ydpi": 424.069
    },
    "gender": "FEMALE",
    "name": "Loredana",
    "surname": "abbatelli"
  },
  "touch_down_points": [
    {
      "time": 0,
      "component": 0,
      "x": 730.0,
      "y": 334.0
    },
    {
      "time": 1437,
      "component": 1,
      "x": 1056.0,
      "y": 546.0
    },
    {
      "time": 2203,
      "component": 2,
      "x": 729.0,
      "y": 360.0
    },
    {
      "time": 3817,
      "component": 3,
      "x": 1121.0,
      "y": 537.0
    },
    {
      "time": 6865,
      "component": 4,
      "x": 1068.0,
      "y": 572.0
    },
    {
      "time": 7564,
      "component": 5,
      "x": 1136.0,
      "y": 554.0
    },
    {
      "time": 9611,
      "component": 6,
      "x": 1223.0,
      "y": 608.0
    },
    {
      "time": 10196,
      "component": 7,
      "x": 1273.0,
      "y": 656.0
    },
    {
      "time": 10625,
      "component": 8,
      "x": 1274.0,
      "y": 739.0
    },
    {
      "time": 11868,
      "component": 9,
      "x": 1129.0,
      "y": 487.0
    },
    {
      "time": 12674,
      "component": 10,
      "x": 1104.0,
      "y": 525.0
    },
    {
      "time": 13340,
      "component": 11,
      "x": 1114.0,
      "y": 509.0
    },
    {
      "time": 14031,
      "component": 12,
      "x": 1121.0,
      "y": 523.0
    }
  ],
  "touch_up_points": [
    {
      "time": 637,
      "component": 0,
      "x": 1052.0,
      "y": 561.0
    },
    {
      "time": 1676,
      "component": 1,
      "x": 1096.0,
      "y": 517.0
    },
    {
      "time": 3293,
      "component": 2,
      "x": 1123.44,
      "y": 910.22
    },
    {
      "time": 5905,
      "component": 3,
      "x": 1152.0,
      "y": 941.2232
    },
    {
      "time": 7180,
      "component": 4,
      "x": 1132.0,
      "y": 962.0
    },
    {
      "time": 7919,
      "component": 5,
      "x": 1167.0,
      "y": 896.0
    },
    {
      "time": 9844,
      "component": 6,
      "x": 1291.0,
      "y": 550.0
    },
    {
      "time": 10344,
      "component": 7,
      "x": 1309.0,
      "y": 630.0
    },
    {
      "time": 10777,
      "component": 8,
      "x": 1296.0,
      "y": 707.0
    },
    {
      "time": 12083,
      "component": 9,
      "x": 1244.3981,
      "y": 387.8017
    },
    {
      "time": 12865,
      "component": 10,
      "x": 1225.103,
      "y": 380.5279
    },
    {
      "time": 13532,
      "component": 11,
      "x": 1187.7993,
      "y": 385.65048
    },
    {
      "time": 14227,
      "component": 12,
      "x": 1169.708,
      "y": 345.26797
    }
  ]
}