{
  "date": "Mon Jan 28 12:08:21 GMT+01:00 2019",
  "item": "7",
  "item_index": 7,
  "movement_points": [
    {
      "time": 0,
      "component": 0,
      "x": 890.0,
      "y": 539.0
    },
    {
      "time": 14,
      "component": 0,
      "x": 890.0,
      "y": 539.0
    },
    {
      "time": 31,
      "component": 0,
      "x": 890.0,
      "y": 539.0
    },
    {
      "time": 47,
      "component": 0,
      "x": 890.0,
      "y": 539.0
    },
    {
      "time": 64,
      "component": 0,
      "x": 890.0,
      "y": 539.0
    },
    {
      "time": 80,
      "component": 0,
      "x": 890.0,
      "y": 539.0
    },
    {
      "time": 98,
      "component": 0,
      "x": 894.4996,
      "y": 524.00165
    },
    {
      "time": 114,
      "component": 0,
      "x": 901.72754,
      "y": 508.0599
    },
    {
      "time": 130,
      "component": 0,
      "x": 910.0277,
      "y": 493.2015
    },
    {
      "time": 147,
      "component": 0,
      "x": 919.23865,
      "y": 482.76135
    },
    {
      "time": 164,
      "component": 0,
      "x": 929.26624,
      "y": 475.24023
    },
    {
      "time": 180,
      "component": 0,
      "x": 941.5179,
      "y": 470.49405
    },
    {
      "time": 197,
      "component": 0,
      "x": 959.21423,
      "y": 467.75397
    },
    {
      "time": 214,
      "component": 0,
      "x": 981.7473,
      "y": 468.0
    },
    {
      "time": 230,
      "component": 0,
      "x": 1002.5474,
      "y": 470.25473
    },
    {
      "time": 247,
      "component": 0,
      "x": 1017.7598,
      "y": 474.5028
    },
    {
      "time": 264,
      "component": 0,
      "x": 1029.1357,
      "y": 479.68146
    },
    {
      "time": 280,
      "component": 0,
      "x": 1033.4961,
      "y": 488.2404
    },
    {
      "time": 297,
      "component": 0,
      "x": 1030.5022,
      "y": 499.99146
    },
    {
      "time": 314,
      "component": 0,
      "x": 1021.789,
      "y": 527.39075
    },
    {
      "time": 331,
      "component": 0,
      "x": 1009.53644,
      "y": 555.1711
    },
    {
      "time": 347,
      "component": 0,
      "x": 998.8437,
      "y": 581.0064
    },
    {
      "time": 364,
      "component": 0,
      "x": 987.8358,
      "y": 603.794
    },
    {
      "time": 380,
      "component": 0,
      "x": 980.2678,
      "y": 623.1966
    },
    {
      "time": 397,
      "component": 0,
      "x": 974.5175,
      "y": 636.4474
    },
    {
      "time": 414,
      "component": 0,
      "x": 972.7568,
      "y": 646.97284
    },
    {
      "time": 431,
      "component": 0,
      "x": 973.0,
      "y": 652.2458
    },
    {
      "time": 440,
      "component": 0,
      "x": 974.0,
      "y": 654.0
    },
    {
      "time": 566,
      "component": 1,
      "x": 969.0,
      "y": 593.0
    },
    {
      "time": 573,
      "component": 1,
      "x": 969.0,
      "y": 593.0
    },
    {
      "time": 582,
      "component": 1,
      "x": 969.0,
      "y": 593.0
    },
    {
      "time": 597,
      "component": 1,
      "x": 969.0,
      "y": 593.0
    },
    {
      "time": 614,
      "component": 1,
      "x": 969.0,
      "y": 593.0
    },
    {
      "time": 630,
      "component": 1,
      "x": 969.0,
      "y": 593.0
    },
    {
      "time": 647,
      "component": 1,
      "x": 991.6935,
      "y": 588.7551
    },
    {
      "time": 664,
      "component": 1,
      "x": 1020.71844,
      "y": 591.4648
    },
    {
      "time": 680,
      "component": 1,
      "x": 1071.4222,
      "y": 605.9761
    },
    {
      "time": 690,
      "component": 1,
      "x": 1091.0,
      "y": 617.0
    }
  ],
  "sampled_points": [
    {
      "component": 0,
      "x": 890.0,
      "y": 539.0
    },
    {
      "component": 0,
      "x": 891.2963,
      "y": 534.67896
    },
    {
      "component": 0,
      "x": 892.8636,
      "y": 529.5249
    },
    {
      "component": 0,
      "x": 894.4563,
      "y": 524.91156
    },
    {
      "component": 0,
      "x": 896.29816,
      "y": 520.21204
    },
    {
      "component": 0,
      "x": 898.37683,
      "y": 515.45233
    },
    {
      "component": 0,
      "x": 900.5287,
      "y": 510.88754
    },
    {
      "component": 0,
      "x": 902.7706,
      "y": 506.41382
    },
    {
      "component": 0,
      "x": 905.1027,
      "y": 502.03113
    },
    {
      "component": 0,
      "x": 907.63104,
      "y": 497.62375
    },
    {
      "component": 0,
      "x": 910.3144,
      "y": 493.5052
    },
    {
      "component": 0,
      "x": 913.36646,
      "y": 489.46945
    },
    {
      "component": 0,
      "x": 916.73596,
      "y": 485.69626
    },
    {
      "component": 0,
      "x": 920.3646,
      "y": 482.19095
    },
    {
      "component": 0,
      "x": 924.11127,
      "y": 479.10706
    },
    {
      "component": 0,
      "x": 928.2083,
      "y": 476.35214
    },
    {
      "component": 0,
      "x": 932.65405,
      "y": 474.02252
    },
    {
      "component": 0,
      "x": 937.25354,
      "y": 472.19055
    },
    {
      "component": 0,
      "x": 942.1652,
      "y": 470.75314
    },
    {
      "component": 0,
      "x": 946.908,
      "y": 469.7174
    },
    {
      "component": 0,
      "x": 951.9121,
      "y": 468.89856
    },
    {
      "component": 0,
      "x": 956.8436,
      "y": 468.34897
    },
    {
      "component": 0,
      "x": 961.85767,
      "y": 468.0173
    },
    {
      "component": 0,
      "x": 966.81934,
      "y": 467.87714
    },
    {
      "component": 0,
      "x": 972.0045,
      "y": 467.8983
    },
    {
      "component": 0,
      "x": 977.1228,
      "y": 468.03964
    },
    {
      "component": 0,
      "x": 982.14905,
      "y": 468.28763
    },
    {
      "component": 0,
      "x": 987.0834,
      "y": 468.64224
    },
    {
      "component": 0,
      "x": 991.92566,
      "y": 469.1035
    },
    {
      "component": 0,
      "x": 997.04333,
      "y": 469.73505
    },
    {
      "component": 0,
      "x": 1001.82135,
      "y": 470.49893
    },
    {
      "component": 0,
      "x": 1006.86664,
      "y": 471.53784
    },
    {
      "component": 0,
      "x": 1011.70386,
      "y": 472.82236
    },
    {
      "component": 0,
      "x": 1016.71497,
      "y": 474.42075
    },
    {
      "component": 0,
      "x": 1021.24396,
      "y": 476.1361
    },
    {
      "component": 0,
      "x": 1025.6536,
      "y": 478.2373
    },
    {
      "component": 0,
      "x": 1029.4963,
      "y": 481.32205
    },
    {
      "component": 0,
      "x": 1031.9846,
      "y": 485.56213
    },
    {
      "component": 0,
      "x": 1032.5848,
      "y": 490.4469
    },
    {
      "component": 0,
      "x": 1031.7201,
      "y": 495.1858
    },
    {
      "component": 0,
      "x": 1030.3793,
      "y": 499.94812
    },
    {
      "component": 0,
      "x": 1028.9601,
      "y": 504.68323
    },
    {
      "component": 0,
      "x": 1027.4973,
      "y": 509.40918
    },
    {
      "component": 0,
      "x": 1025.8579,
      "y": 514.5902
    },
    {
      "component": 0,
      "x": 1024.3113,
      "y": 519.2395
    },
    {
      "component": 0,
      "x": 1022.66315,
      "y": 523.8997
    },
    {
      "component": 0,
      "x": 1020.91345,
      "y": 528.57086
    },
    {
      "component": 0,
      "x": 1019.06213,
      "y": 533.253
    },
    {
      "component": 0,
      "x": 1017.10925,
      "y": 537.94604
    },
    {
      "component": 0,
      "x": 1015.05365,
      "y": 542.66376
    },
    {
      "component": 0,
      "x": 1012.989,
      "y": 547.382
    },
    {
      "component": 0,
      "x": 1010.97015,
      "y": 552.04315
    },
    {
      "component": 0,
      "x": 1008.9972,
      "y": 556.64703
    },
    {
      "component": 0,
      "x": 1007.0701,
      "y": 561.1937
    },
    {
      "component": 0,
      "x": 1005.1889,
      "y": 565.6833
    },
    {
      "component": 0,
      "x": 1003.26733,
      "y": 570.304
    },
    {
      "component": 0,
      "x": 1001.2485,
      "y": 575.05304
    },
    {
      "component": 0,
      "x": 999.2185,
      "y": 579.6945
    },
    {
      "component": 0,
      "x": 997.1774,
      "y": 584.2286
    },
    {
      "component": 0,
      "x": 995.12524,
      "y": 588.6551
    },
    {
      "component": 0,
      "x": 993.02045,
      "y": 593.06274
    },
    {
      "component": 0,
      "x": 990.7352,
      "y": 597.90497
    },
    {
      "component": 0,
      "x": 988.6119,
      "y": 602.5878
    },
    {
      "component": 0,
      "x": 986.6504,
      "y": 607.11145
    },
    {
      "component": 0,
      "x": 984.8508,
      "y": 611.4758
    },
    {
      "component": 0,
      "x": 983.0366,
      "y": 616.0841
    },
    {
      "component": 0,
      "x": 981.1947,
      "y": 620.7032
    },
    {
      "component": 0,
      "x": 979.2781,
      "y": 625.38153
    },
    {
      "component": 0,
      "x": 977.3966,
      "y": 629.813
    },
    {
      "component": 0,
      "x": 975.411,
      "y": 634.90643
    },
    {
      "component": 0,
      "x": 974.0659,
      "y": 639.56415
    },
    {
      "component": 0,
      "x": 973.2333,
      "y": 644.3717
    },
    {
      "component": 0,
      "x": 972.86694,
      "y": 649.2604
    },
    {
      "component": 0,
      "x": 973.99976,
      "y": 653.9996
    },
    {
      "component": 1,
      "x": 969.0,
      "y": 593.0
    },
    {
      "component": 1,
      "x": 973.74274,
      "y": 592.11285
    },
    {
      "component": 1,
      "x": 978.679,
      "y": 591.1895
    },
    {
      "component": 1,
      "x": 983.62427,
      "y": 590.3461
    },
    {
      "component": 1,
      "x": 988.5901,
      "y": 589.8242
    },
    {
      "component": 1,
      "x": 993.67224,
      "y": 589.5967
    },
    {
      "component": 1,
      "x": 998.53845,
      "y": 589.63
    },
    {
      "component": 1,
      "x": 1003.6147,
      "y": 589.8939
    },
    {
      "component": 1,
      "x": 1008.56213,
      "y": 590.36035
    },
    {
      "component": 1,
      "x": 1013.62744,
      "y": 591.07294
    },
    {
      "component": 1,
      "x": 1018.41125,
      "y": 591.91693
    },
    {
      "component": 1,
      "x": 1023.4861,
      "y": 592.9525
    },
    {
      "component": 1,
      "x": 1028.1869,
      "y": 594.0155
    },
    {
      "component": 1,
      "x": 1033.1708,
      "y": 595.23267
    },
    {
      "component": 1,
      "x": 1037.9026,
      "y": 596.461
    },
    {
      "component": 1,
      "x": 1042.7457,
      "y": 597.7814
    },
    {
      "component": 1,
      "x": 1047.8068,
      "y": 599.22064
    },
    {
      "component": 1,
      "x": 1052.7198,
      "y": 600.6743
    },
    {
      "component": 1,
      "x": 1057.3074,
      "y": 602.09155
    },
    {
      "component": 1,
      "x": 1062.2479,
      "y": 603.6988
    },
    {
      "component": 1,
      "x": 1066.8174,
      "y": 605.2823
    },
    {
      "component": 1,
      "x": 1071.6537,
      "y": 607.09814
    },
    {
      "component": 1,
      "x": 1076.1385,
      "y": 608.9729
    },
    {
      "component": 1,
      "x": 1080.6299,
      "y": 611.1666
    },
    {
      "component": 1,
      "x": 1084.9075,
      "y": 613.5694
    },
    {
      "component": 1,
      "x": 1089.2643,
      "y": 616.02264
    }
  ],
  "session_data": {
    "age": 24,
    "configuration": {
      "guide_lines": true,
      "items": [
        "0",
        "1",
        "2",
        "3",
        "4",
        "5",
        "6",
        "7",
        "8",
        "9"
      ],
      "repetitions": 10,
      "repetitions_label": "Ripetizioni",
      "title": "Disegna il numero: "
    },
    "date": "28.01.2019.12.08",
    "device_data": {
      "device_finger_print": "HUAWEI/WAS-LX1A/HWWAS-H:8.0.0/HUAWEIWAS-LX1A/377(C432):user/release-keys",
      "device_model": "WAS-LX1A",
      "heigth_pixels": 1080,
      "width_pixels": 1795,
      "xdpi": 422.03,
      "ydpi": 424.069
    },
    "gender": "MALE",
    "name": "Luca",
    "surname": "Moschella"
  },
  "touch_down_points": [
    {
      "time": 0,
      "component": 0,
      "x": 890.0,
      "y": 539.0
    },
    {
      "time": 566,
      "component": 1,
      "x": 969.0,
      "y": 593.0
    }
  ],
  "touch_up_points": [
    {
      "time": 441,
      "component": 0,
      "x": 974.0,
      "y": 654.0
    },
    {
      "time": 691,
      "component": 1,
      "x": 1091.0,
      "y": 617.0
    }
  ]
}